{
  "show": "Seinfeld",
  "slug": "seinfeld",
  "season": 7,
  "episode_number": 19,
  "title": "The Wig Master",
  "humor_index": 70.5,
  "jpm": 2.23,
  "avg_craft": 6.75,
  "avg_impact": 6.4,
  "total_jokes": 52,
  "war": 29.9,
  "dominant_joke_types": "[\"character_comedy\", \"absurdist\", \"observational\"]",
  "standout_joke_ids": "[22, 30, 43]",
  "weakest_section": "16:00-17:00",
  "jokes": [
    {
      "index": 1,
      "text": "Have you noticed that every place has that tip jar on the counter?",
      "characters": [
        "Jerry"
      ],
      "joke_types": [
        "observational"
      ],
      "setup": "Opening observational premise about ubiquitous tip jars",
      "punchline": "The observation itself - the universality of tip jars",
      "craft_total": 6.1,
      "impact_score": 5.0,
      "quotability": 4.0,
      "rewatch_bonus": 0,
      "is_callback": 0,
      "explanation": "Classic Jerry observational setup - economical and character-appropriate but not groundbreaking",
      "dialogue": [
        {
          "speaker": "Jerry",
          "line": "Why is there a tip jar everywhere now? I went to a store to buy a lightbulb. A lightbulb! The guy behind the counter points to a tip jar. What am I tipping for? You took it off the shelf. It was right there."
        }
      ]
    },
    {
      "index": 2,
      "text": "What is the service that this tip is for, anyway? I mean, isn't the man basically just turning around?",
      "characters": [
        "Jerry"
      ],
      "joke_types": [
        "observational",
        "absurdist"
      ],
      "setup": "Questioning the nature of service deserving tips",
      "punchline": "Reducing service to just 'turning around'",
      "craft_total": 7.35,
      "impact_score": 7.0,
      "quotability": 6.0,
      "rewatch_bonus": 1,
      "is_callback": 0,
      "explanation": "Brilliant reductionist observation - taking complex service interaction and reducing to physical movement",
      "dialogue": [
        {
          "speaker": "Jerry",
          "line": "What is a tip? A tip is like, extra money you give someone. It's not obligatory, it's a gift. Why do I have to give you a gift for doing your job? That's the job."
        },
        {
          "speaker": "Jerry",
          "line": "You know what a tip should be for? A tip should be for something above and beyond. Not just doing what you're supposed to do."
        },
        {
          "speaker": "Jerry",
          "line": "I went to a coffee place the other day, the guy hands me my coffee, I hand him a dollar. He goes, 'Oh, thank you.' Like I just gave him a kidney. I turned around. That's it. I turned around."
        }
      ]
    },
    {
      "index": 3,
      "text": "I think we're tipping people now just for the absence of outright hostility",
      "characters": [
        "Jerry"
      ],
      "joke_types": [
        "observational",
        "dark_subversive"
      ],
      "setup": "Building on the tip jar premise",
      "punchline": "Reframing tips as payment for not being attacked",
      "craft_total": 7.55,
      "impact_score": 7.5,
      "quotability": 8.0,
      "rewatch_bonus": 1,
      "is_callback": 0,
      "explanation": "Excellent escalation that reframes social courtesy as hostage situation - very quotable",
      "dialogue": [
        {
          "speaker": "Jerry",
          "line": "So now tipping is for not being attacked? What's next, I go to a restaurant, the waiter comes over with a gun, 'You gonna tip me or do I shoot?'"
        },
        {
          "speaker": "Jerry",
          "line": "That's what we've come to. Tips used to mean something. 'Oh, that was great service, here's a little extra.' Now it's extortion. 'Give me money or I'll spit in your food.'"
        }
      ]
    },
    {
      "index": 4,
      "text": "Thanks very much, and here's something extra... for not taking my head... and smashing my face through the glass countertop. Really good service here.",
      "characters": [
        "Jerry"
      ],
      "joke_types": [
        "escalation",
        "absurdist"
      ],
      "setup": "Previous joke about tipping for non-hostility",
      "punchline": "Extreme violent imagery delivered in polite thank-you format",
      "craft_total": 7.25,
      "impact_score": 7.0,
      "quotability": 6.0,
      "rewatch_bonus": 0,
      "is_callback": 0,
      "explanation": "Good escalation with darkly absurd imagery contrasted against polite service language",
      "dialogue": [
        {
          "speaker": "Jerry",
          "line": "Thank you for not stabbing me in the throat with a corkscrew. Thank you for not tying me up and leaving me in the trunk of your car. Thank you for not removing my organs and selling them on the black market. I really appreciate that."
        }
      ]
    },
    {
      "index": 5,
      "text": "Are you out of your mind? You'd suffocate in there. You're lucky to have doors. When I was in the Army...",
      "characters": [
        "Steinbrenner"
      ],
      "joke_types": [
        "character_comedy",
        "escalation"
      ],
      "setup": "George suggesting extending bathroom stall doors",
      "punchline": "Steinbrenner's extreme reaction about suffocation and military reference",
      "craft_total": 6.4,
      "impact_score": 6.0,
      "quotability": 4.0,
      "rewatch_bonus": 1,
      "is_callback": 0,
      "explanation": "Perfect Steinbrenner character moment - bombastic overreaction to mundane suggestion",
      "dialogue": [
        {
          "speaker": "George",
          "line": "You know, we could extend these doors down to the floor. Give people a little privacy."
        },
        {
          "speaker": "Steinbrenner",
          "line": "That's it! That's genius! We'll extend the doors. But wait, what if someone gets trapped in there? They could suffocate! We need air holes. No, no, air holes make it look like a submarine. I served in the war, you know. We had a man get stuck in the torpedo room once. Horrible. Just horrible."
        },
        {
          "speaker": "George",
          "line": "Sir, I was just\u2014"
        },
        {
          "speaker": "Steinbrenner",
          "line": "No, no, it's done. We're extending the doors. Extend them all! This is what leadership looks like!"
        }
      ]
    },
    {
      "index": 6,
      "text": "Big Stein wants a little taste. Come on. Pass it down. That's a good boy.",
      "characters": [
        "Steinbrenner"
      ],
      "joke_types": [
        "character_comedy",
        "absurdist"
      ],
      "setup": "Steinbrenner seeing George's calzone",
      "punchline": "Treating employee like a dog with 'good boy' while demanding food",
      "craft_total": 6.55,
      "impact_score": 6.5,
      "quotability": 6.0,
      "rewatch_bonus": 1,
      "is_callback": 0,
      "explanation": "Classic Steinbrenner treating employees like pets while referring to himself in third person",
      "dialogue": [
        {
          "speaker": "Steinbrenner",
          "line": "What is that?"
        },
        {
          "speaker": "George",
          "line": "It's a calzone."
        },
        {
          "speaker": "Steinbrenner",
          "line": "A calzone? Why are you eating a calzone?"
        },
        {
          "speaker": "George",
          "line": "I was hungry."
        },
        {
          "speaker": "Steinbrenner",
          "line": "You're always eating. You're like a little dog. Good boy! Good boy! Now get me one of those."
        }
      ]
    },
    {
      "index": 7,
      "text": "Big Stein wants an eggplant calzone. He must have one. Everybody out. Hurry up, hurry up.",
      "characters": [
        "Steinbrenner"
      ],
      "joke_types": [
        "character_comedy",
        "escalation"
      ],
      "setup": "Steinbrenner enjoying the calzone",
      "punchline": "Clearing entire meeting for calzone obsession",
      "craft_total": 6.4,
      "impact_score": 6.0,
      "quotability": 5.0,
      "rewatch_bonus": 0,
      "is_callback": 0,
      "explanation": "Good escalation showing Steinbrenner's impulsive nature prioritizing food over business",
      "dialogue": [
        {
          "speaker": "Steinbrenner",
          "line": "This is an amazing calzone. Where did you get this?"
        },
        {
          "speaker": "Steinbrenner",
          "line": "Cancel the meeting. Cancel it. I'm gonna go back to my office and finish this calzone."
        }
      ]
    },
    {
      "index": 8,
      "text": "He bet me that Dustin Hoffman was in Star Wars.",
      "characters": [
        "Elaine"
      ],
      "joke_types": [
        "absurdist",
        "setup_punchline"
      ],
      "setup": "Explaining a bet she won",
      "punchline": "The ridiculous nature of the bet itself",
      "craft_total": 6.7,
      "impact_score": 6.0,
      "quotability": 5.0,
      "rewatch_bonus": 0,
      "is_callback": 0,
      "explanation": "Funny absurd premise - the incongruity is inherently comedic",
      "dialogue": [
        {
          "speaker": "Elaine",
          "line": "I won twenty bucks from Kramer because he said he could go a whole week without saying the word 'the.' He made it three days."
        }
      ]
    },
    {
      "index": 9,
      "text": "Short Jewish guy against Darth Vader? I don't think so.",
      "characters": [
        "Jerry"
      ],
      "joke_types": [
        "observational",
        "character_comedy"
      ],
      "setup": "Dustin Hoffman in Star Wars premise",
      "punchline": "Physical/cultural mismatch with Darth Vader",
      "craft_total": 6.75,
      "impact_score": 6.5,
      "quotability": 6.0,
      "rewatch_bonus": 0,
      "is_callback": 0,
      "explanation": "Good observational humor about physical/tonal mismatch in casting",
      "dialogue": [
        {
          "speaker": "Jerry",
          "line": "So Dustin Hoffman as Darth Vader? I'm trying to picture this. Dustin Hoffman is like five-foot-nothing, and Darth Vader is this imposing, seven-foot figure in all black. He walks into a room, everyone trembles. Dustin Hoffman walks in, people go, 'Is that the caterer?'"
        }
      ]
    },
    {
      "index": 10,
      "text": "Hey, Elaine, you gotta feel my pants.",
      "characters": [
        "Kramer"
      ],
      "joke_types": [
        "character_comedy"
      ],
      "setup": "Kramer excited about warm clothes from dryer",
      "punchline": "Innocent request that sounds sexual",
      "craft_total": 6.3,
      "impact_score": 6.0,
      "quotability": 7.0,
      "rewatch_bonus": 0,
      "is_callback": 0,
      "explanation": "Classic double entendre - works because Kramer's innocent enthusiasm makes it funnier",
      "dialogue": [
        {
          "speaker": "Kramer",
          "line": "These are warm!"
        },
        {
          "speaker": "Jerry",
          "line": "Yeah, they just came out of the dryer."
        },
        {
          "speaker": "Kramer",
          "line": "Can I have some of your stuff in my dryer?"
        }
      ]
    },
    {
      "index": 11,
      "text": "I'll see you later. - All right. You don't know what you're missing.",
      "characters": [
        "Elaine",
        "Kramer"
      ],
      "joke_types": [
        "reaction_beat"
      ],
      "setup": "Elaine declining to feel Kramer's pants",
      "punchline": "Kramer's persistent innocent enthusiasm about the warmth",
      "craft_total": 5.95,
      "impact_score": 5.5,
      "quotability": 4.0,
      "rewatch_bonus": 0,
      "is_callback": 0,
      "explanation": "Follow-up that extends the double entendre naturally",
      "dialogue": [
        {
          "speaker": "Kramer",
          "line": "Come on, just feel it. Feel how warm it is."
        },
        {
          "speaker": "Elaine",
          "line": "No, Kramer, I'm not feeling your pants."
        },
        {
          "speaker": "Kramer",
          "line": "You don't understand. These are special pants. The warmth is incredible."
        },
        {
          "speaker": "Elaine",
          "line": "I don't care how warm they are."
        },
        {
          "speaker": "Kramer",
          "line": "Just one feel. One little feel and you'll see what I'm talking about."
        }
      ]
    },
    {
      "index": 12,
      "text": "Bold and beautiful.",
      "characters": [
        "Jerry"
      ],
      "joke_types": [
        "wordplay_pun",
        "meta_self_referential"
      ],
      "setup": "Describing Nicki as bold and beautiful",
      "punchline": "Reference to soap opera 'The Bold and the Beautiful'",
      "craft_total": 5.25,
      "impact_score": 4.0,
      "quotability": 3.0,
      "rewatch_bonus": 0,
      "is_callback": 0,
      "explanation": "Simple pop culture reference without much twist - functional but not clever",
      "dialogue": [
        {
          "speaker": "Jerry",
          "line": "She's bold and beautiful."
        },
        {
          "speaker": "Jerry",
          "line": "Like the soap opera."
        }
      ]
    },
    {
      "index": 13,
      "text": "The pita pocket prevents it from dripping.",
      "characters": [
        "George"
      ],
      "joke_types": [
        "observational",
        "absurdist"
      ],
      "setup": "George praising his calzone eating method",
      "punchline": "Treating pita pocket like revolutionary technology",
      "craft_total": 6.35,
      "impact_score": 5.5,
      "quotability": 5.0,
      "rewatch_bonus": 0,
      "is_callback": 0,
      "explanation": "Good George moment - finding mundane innovation in simple food solution",
      "dialogue": [
        {
          "speaker": "George",
          "line": "You see, the key is in the way you eat it. You fold it, you see? Like this. It's not just a pocket of pita bread, it's a delivery system. A revolutionary delivery system."
        }
      ]
    },
    {
      "index": 14,
      "text": "If people can't hold onto things, tough luck.",
      "characters": [
        "Steinbrenner"
      ],
      "joke_types": [
        "character_comedy",
        "dark_subversive"
      ],
      "setup": "Discussion about lost and found",
      "punchline": "Steinbrenner's harsh dismissal of human forgetfulness",
      "craft_total": 6.7,
      "impact_score": 6.0,
      "quotability": 5.0,
      "rewatch_bonus": 0,
      "is_callback": 0,
      "explanation": "Perfect Steinbrenner - ruthless businessman attitude toward basic human needs",
      "dialogue": [
        {
          "speaker": "Steinbrenner",
          "line": "You lose something, it's gone. That's it. No lost and found. You know why? Because people are careless. And I don't reward carelessness."
        }
      ]
    },
    {
      "index": 15,
      "text": "Who did you bet was in Star Wars? Sammy Davis Jr.?",
      "characters": [
        "Jerry"
      ],
      "joke_types": [
        "callback",
        "escalation"
      ],
      "setup": "Meeting Todd who made the Dustin Hoffman bet",
      "punchline": "Suggesting even more unlikely Star Wars casting",
      "craft_total": 6.75,
      "impact_score": 6.5,
      "quotability": 5.0,
      "rewatch_bonus": 0,
      "is_callback": 1,
      "explanation": "Good callback escalation - Sammy Davis Jr. even more absurd than Dustin Hoffman",
      "dialogue": [
        {
          "speaker": "Jerry",
          "line": "You know who should play Luke Skywalker? Dustin Hoffman."
        },
        {
          "speaker": "Todd",
          "line": "Dustin Hoffman? He's too short!"
        },
        {
          "speaker": "Jerry",
          "line": "Well, what about Carrot Top as Han Solo?"
        },
        {
          "speaker": "Todd",
          "line": "Carrot Top? Are you insane?"
        },
        {
          "speaker": "Jerry",
          "line": "And Phyllis Diller as Princess Leia."
        },
        {
          "speaker": "Todd",
          "line": "This is ridiculous."
        },
        {
          "speaker": "Jerry",
          "line": "With Bea Arthur as Darth Vader."
        }
      ]
    },
    {
      "index": 16,
      "text": "Two tickets. Means to an End. - Told you.",
      "characters": [
        "Nicki",
        "Jerry"
      ],
      "joke_types": [
        "character_comedy",
        "setup_punchline"
      ],
      "setup": "Jerry doubts Nicki can get sold-out tickets",
      "punchline": "She effortlessly succeeds, proving her power",
      "craft_total": 6.35,
      "impact_score": 5.5,
      "quotability": 3.0,
      "rewatch_bonus": 0,
      "is_callback": 0,
      "explanation": "Establishes Nicki's power theme but fairly predictable payoff",
      "dialogue": [
        {
          "speaker": "Jerry",
          "line": "There's no way you can get tickets to that show. It's been sold out for months."
        },
        {
          "speaker": "Nicki",
          "line": "Watch this."
        },
        {
          "speaker": "Nicki",
          "line": "I'm calling the box office right now."
        },
        {
          "speaker": "Jerry",
          "line": "Good luck with that."
        },
        {
          "speaker": "Nicki",
          "line": "Hi, yes, I'm looking for two tickets to... uh-huh... tomorrow night... perfect, we'll take them. Thank you."
        },
        {
          "speaker": "Nicki",
          "line": "Done."
        },
        {
          "speaker": "Jerry",
          "line": "How did you... what did you do?"
        },
        {
          "speaker": "Nicki",
          "line": "I just asked. Apparently they always hold a few back."
        }
      ]
    },
    {
      "index": 17,
      "text": "They're really building a Utopian society up there.",
      "characters": [
        "Jerry"
      ],
      "joke_types": [
        "irony_sarcasm",
        "observational"
      ],
      "setup": "George describing Yankees implementing his lost and found idea",
      "punchline": "Sarcastically calling minor stadium improvement 'Utopian'",
      "craft_total": 6.65,
      "impact_score": 6.0,
      "quotability": 6.0,
      "rewatch_bonus": 0,
      "is_callback": 0,
      "explanation": "Good sarcastic deflation of George's pride in minor accomplishment",
      "dialogue": [
        {
          "speaker": "George",
          "line": "The Yankees are implementing my lost and found idea!"
        },
        {
          "speaker": "Jerry",
          "line": "Oh sure, they've created a utopia at Yankee Stadium."
        }
      ]
    },
    {
      "index": 18,
      "text": "I'm like a drug dealer. I got the guy hooked.",
      "characters": [
        "George"
      ],
      "joke_types": [
        "absurdist",
        "character_comedy"
      ],
      "setup": "George explaining his influence over Steinbrenner through calzones",
      "punchline": "Comparing food delivery to drug dealing",
      "craft_total": 7.35,
      "impact_score": 7.0,
      "quotability": 7.0,
      "rewatch_bonus": 1,
      "is_callback": 0,
      "explanation": "Excellent escalation - George's grandiose self-image applied to lunch delivery",
      "dialogue": [
        {
          "speaker": "George",
          "line": "It's like a drug deal. He's the addict, I'm the dealer. I control the supply, I control him."
        }
      ]
    },
    {
      "index": 19,
      "text": "So then, as I'm leaving, he gives me a look like 'Thanks for nothing.'",
      "characters": [
        "George"
      ],
      "joke_types": [
        "observational",
        "cringe_discomfort"
      ],
      "setup": "Tip jar worker looked away during George's tip",
      "punchline": "Getting no credit for good deed due to timing",
      "craft_total": 7.0,
      "impact_score": 6.5,
      "quotability": 5.0,
      "rewatch_bonus": 0,
      "is_callback": 1,
      "explanation": "Good callback that adds personal stakes to Jerry's earlier observation",
      "dialogue": [
        {
          "speaker": "George",
          "line": "I put a dollar in the tip jar. The guy didn't even see it. He looked away right when I did it."
        },
        {
          "speaker": "Jerry",
          "line": "So what's the problem?"
        },
        {
          "speaker": "George",
          "line": "What's the problem? I did a good deed and nobody saw it! It's like it never happened!"
        },
        {
          "speaker": "Jerry",
          "line": "George, a good deed is a good deed whether someone sees it or not."
        },
        {
          "speaker": "George",
          "line": "No, no, no. The whole point of doing a good deed is so people know you did it. Otherwise, what's the point?"
        }
      ]
    },
    {
      "index": 20,
      "text": "So you don't make a habit of giving to the blind?",
      "characters": [
        "Jerry"
      ],
      "joke_types": [
        "dark_subversive",
        "setup_punchline"
      ],
      "setup": "George complaining about unacknowledged tipping",
      "punchline": "Comparing tip jar worker to blind person needing acknowledgment",
      "craft_total": 7.4,
      "impact_score": 7.5,
      "quotability": 8.0,
      "rewatch_bonus": 1,
      "is_callback": 0,
      "explanation": "Brilliant dark turn that exposes the vanity in charitable giving - very quotable",
      "dialogue": [
        {
          "speaker": "George",
          "line": "You know, the thing about these tip jars is nobody ever acknowledges the tip. You put money in, and nothing. No thank you, no nod, no recognition whatsoever."
        },
        {
          "speaker": "Jerry",
          "line": "What do you want them to do?"
        },
        {
          "speaker": "George",
          "line": "I don't know, something! It's like being invisible. You might as well be a blind person putting money in a tip jar \u2014 at least they have an excuse for not seeing you."
        }
      ]
    },
    {
      "index": 21,
      "text": "Not bills.",
      "characters": [
        "George"
      ],
      "joke_types": [
        "deadpan_understatement",
        "dark_subversive"
      ],
      "setup": "Jerry's question about giving to the blind",
      "punchline": "George's matter-of-fact admission of discrimination by denomination",
      "craft_total": 7.25,
      "impact_score": 7.0,
      "quotability": 7.0,
      "rewatch_bonus": 1,
      "is_callback": 0,
      "explanation": "Perfect George - economical admission of petty selfishness delivered matter-of-factly",
      "dialogue": [
        {
          "speaker": "Jerry",
          "line": "You give to the blind?"
        },
        {
          "speaker": "George",
          "line": "I give to the blind, the crippled, and the kids. But I draw the line at the deaf."
        }
      ]
    },
    {
      "index": 22,
      "text": "She's like a beautiful Godzilla. And I'm thousands of fleeing Japanese.",
      "characters": [
        "Jerry"
      ],
      "joke_types": [
        "absurdist",
        "escalation"
      ],
      "setup": "Describing Nicki's power to get whatever she wants",
      "punchline": "Extended monster movie metaphor with himself as victims",
      "craft_total": 7.65,
      "impact_score": 8.0,
      "quotability": 9.0,
      "rewatch_bonus": 1,
      "is_callback": 0,
      "explanation": "Brilliant extended metaphor that perfectly captures power dynamic - highly quotable and visual",
      "dialogue": [
        {
          "speaker": "Jerry",
          "line": "She's like a monster. She destroys everything in her path. She comes into a room, it's like Godzilla stomping through downtown Tokyo. 'Oh no, here she comes!' Buildings are falling, people are running, screaming. And I'm like a tiny building. I'm like a little office building, and she just steps on me, crushes me, and moves on to the next city."
        }
      ]
    },
    {
      "index": 23,
      "text": "I need quarters for the dryer. - Why can't you do this on your table? - Because I don't have a table.",
      "characters": [
        "Kramer",
        "Jerry",
        "Kramer"
      ],
      "joke_types": [
        "character_comedy",
        "absurdist"
      ],
      "setup": "Kramer counting change on Jerry's counter",
      "punchline": "Casual admission of not owning basic furniture",
      "craft_total": 6.55,
      "impact_score": 6.0,
      "quotability": 4.0,
      "rewatch_bonus": 0,
      "is_callback": 0,
      "explanation": "Good Kramer moment revealing his unconventional living situation matter-of-factly",
      "dialogue": [
        {
          "speaker": "Kramer",
          "line": "You know, I'm a little short. You got any change?"
        },
        {
          "speaker": "Jerry",
          "line": "Kramer, what do you need money for? Don't you have a job?"
        },
        {
          "speaker": "Kramer",
          "line": "Well, I gotta pay my rent."
        },
        {
          "speaker": "Jerry",
          "line": "Your rent? I thought you lived on my couch."
        },
        {
          "speaker": "Kramer",
          "line": "I do live on your couch. That's my rent."
        }
      ]
    },
    {
      "index": 24,
      "text": "He's found a dating loophole.",
      "characters": [
        "Jerry"
      ],
      "joke_types": [
        "observational",
        "setup_punchline"
      ],
      "setup": "Explaining Todd's betting strategy to avoid rejection",
      "punchline": "Reframing elaborate scheme as legal/technical workaround",
      "craft_total": 7.55,
      "impact_score": 7.5,
      "quotability": 8.5,
      "rewatch_bonus": 1,
      "is_callback": 0,
      "explanation": "Excellent concept - applying legal/technical language to social interaction. Very Seinfeldian.",
      "dialogue": [
        {
          "speaker": "Jerry",
          "line": "So Todd's betting strategy is basically: he places bets, but he frames it as a legal technicality so when he loses, he can argue it doesn't count."
        },
        {
          "speaker": "Jerry",
          "line": "It's the perfect loophole. He's not really betting, he's just... exploring the gray area of what constitutes a wager."
        }
      ]
    },
    {
      "index": 25,
      "text": "That's just because you're a jackass.",
      "characters": [
        "Elaine"
      ],
      "joke_types": [
        "character_comedy"
      ],
      "setup": "Jerry pointing out he never walks her home",
      "punchline": "Elaine's blunt assessment of Jerry's character",
      "craft_total": 6.25,
      "impact_score": 6.5,
      "quotability": 6.0,
      "rewatch_bonus": 0,
      "is_callback": 0,
      "explanation": "Good character moment - Elaine's directness cutting through Jerry's logic",
      "dialogue": [
        {
          "speaker": "Elaine",
          "line": "You never walk me home."
        },
        {
          "speaker": "Jerry",
          "line": "What do you mean? I walk you home."
        },
        {
          "speaker": "Elaine",
          "line": "No you don't. You walk me to the corner, and then you turn back."
        },
        {
          "speaker": "Jerry",
          "line": "Well, the corner is pretty much your block."
        },
        {
          "speaker": "Elaine",
          "line": "Jerry, you're a very selfish person."
        }
      ]
    },
    {
      "index": 26,
      "text": "Crazy like a man.",
      "characters": [
        "Jerry"
      ],
      "joke_types": [
        "wordplay_pun",
        "misdirection"
      ],
      "setup": "Elaine calling him crazy",
      "punchline": "Twisting 'crazy like a fox' to emphasize gender",
      "craft_total": 6.15,
      "impact_score": 5.5,
      "quotability": 5.0,
      "rewatch_bonus": 0,
      "is_callback": 0,
      "explanation": "Decent wordplay twist on common expression but not particularly clever",
      "dialogue": [
        {
          "speaker": "Elaine",
          "line": "You're crazy."
        },
        {
          "speaker": "Jerry",
          "line": "Crazy like a fox."
        }
      ]
    },
    {
      "index": 27,
      "text": "So you and I are kind of like countrymen. Paisanos.",
      "characters": [
        "George"
      ],
      "joke_types": [
        "character_comedy",
        "cringe_discomfort"
      ],
      "setup": "George trying to bond with calzone shop owner",
      "punchline": "Awkward attempt at ethnic kinship based on surnames",
      "craft_total": 6.4,
      "impact_score": 6.0,
      "quotability": 4.0,
      "rewatch_bonus": 0,
      "is_callback": 0,
      "explanation": "Classic George cringe - inappropriate familiarity based on ethnic assumptions",
      "dialogue": [
        {
          "speaker": "George",
          "line": "You know, I've been thinking about something. My name is Costanza. That's Italian."
        },
        {
          "speaker": "Calzone Shop Owner",
          "line": "Yes, I know."
        },
        {
          "speaker": "George",
          "line": "And you're... you're Italian too, right?"
        },
        {
          "speaker": "Calzone Shop Owner",
          "line": "Yes."
        },
        {
          "speaker": "George",
          "line": "So we're like... we're practically family! We should be friends. We could do things together. Get some pasta, maybe catch a Knicks game."
        },
        {
          "speaker": "Calzone Shop Owner",
          "line": "I don't think so."
        }
      ]
    },
    {
      "index": 28,
      "text": "Hey, hey, you steal my money? - No, you don't understand. I wasn't taking it out.",
      "characters": [
        "Antonio",
        "George"
      ],
      "joke_types": [
        "cringe_discomfort",
        "physical_slapstick"
      ],
      "setup": "George's tip being misinterpreted as theft",
      "punchline": "The complete reversal of his good intention",
      "craft_total": 7.2,
      "impact_score": 7.0,
      "quotability": 4.0,
      "rewatch_bonus": 0,
      "is_callback": 1,
      "explanation": "Excellent payoff to tip jar storyline - George's scheme backfires spectacularly",
      "dialogue": [
        {
          "speaker": "George",
          "line": "I left a twenty dollar bill on the table for the waitress."
        },
        {
          "speaker": "Antonio",
          "line": "You stole from us?"
        },
        {
          "speaker": "George",
          "line": "No, no, it's a tip! It's for good service."
        },
        {
          "speaker": "Antonio",
          "line": "You leave money at a crime scene, we call the police."
        }
      ]
    },
    {
      "index": 29,
      "text": "From 1973 to 1982, I ate the exact same lunch every day. Turkey chilli in a bowl made out of bread.",
      "characters": [
        "Steinbrenner"
      ],
      "joke_types": [
        "character_comedy",
        "absurdist"
      ],
      "setup": "Steinbrenner explaining his consistency preference",
      "punchline": "Obsessive routine with bizarre food choice",
      "craft_total": 7.25,
      "impact_score": 7.0,
      "quotability": 6.0,
      "rewatch_bonus": 1,
      "is_callback": 0,
      "explanation": "Perfect Steinbrenner - obsessive behavior with specific absurd details",
      "dialogue": [
        {
          "speaker": "Steinbrenner",
          "line": "I have a very strict routine. Every morning, I wake up at 6 AM sharp. I have exactly two cups of coffee, black, no sugar. Then I read the sports section for exactly 12 minutes. Then I have my breakfast."
        },
        {
          "speaker": "Steinbrenner",
          "line": "The same breakfast every single day: a bowl of plain oatmeal and a cup of grapefruit juice. But here's the thing - I eat the oatmeal with a fork."
        },
        {
          "speaker": "Steinbrenner",
          "line": "Not a spoon. A fork. My wife thinks I'm crazy, but consistency is what separates the winners from the losers in this world."
        }
      ]
    },
    {
      "index": 30,
      "text": "You eat the chilli, then you eat the bowl. Nothing more satisfying than looking down after lunch and seeing just a table.",
      "characters": [
        "Steinbrenner"
      ],
      "joke_types": [
        "absurdist",
        "escalation"
      ],
      "setup": "Description of bread bowl lunch",
      "punchline": "Poetic satisfaction from complete consumption/disappearance",
      "craft_total": 7.85,
      "impact_score": 7.5,
      "quotability": 7.0,
      "rewatch_bonus": 1,
      "is_callback": 0,
      "explanation": "Brilliant escalation - finding zen satisfaction in total consumption. Very quotable and absurd.",
      "dialogue": [
        {
          "speaker": "Steinbrenner",
          "line": "I'm watching you, and you're eating this thing, and it's like watching a magic trick. The bowl just... disappears."
        },
        {
          "speaker": "Steinbrenner",
          "line": "You eat the bowl! It's brilliant!"
        }
      ]
    },
    {
      "index": 31,
      "text": "Was this whole bet thing just a way of asking me out? - What? - I mean, Dustin Hoffman in Star Wars?",
      "characters": [
        "Elaine",
        "Todd"
      ],
      "joke_types": [
        "callback",
        "setup_punchline"
      ],
      "setup": "Elaine confronting Todd about the bet",
      "punchline": "Using the absurdity of the bet as evidence",
      "craft_total": 6.6,
      "impact_score": 6.0,
      "quotability": 4.0,
      "rewatch_bonus": 0,
      "is_callback": 1,
      "explanation": "Good callback that advances plot while referencing earlier absurdity",
      "dialogue": [
        {
          "speaker": "Elaine",
          "line": "Todd, this bet is completely insane. You're betting me that you can go a whole week without checking your phone?"
        },
        {
          "speaker": "Todd",
          "line": "Yeah, what's so crazy about that?"
        },
        {
          "speaker": "Elaine",
          "line": "What's so crazy? Todd, you check your phone more than you blink. I've seen you walk into fountains because you were texting."
        },
        {
          "speaker": "Todd",
          "line": "That was one time."
        },
        {
          "speaker": "Elaine",
          "line": "It was three times. In one day. At the same fountain."
        }
      ]
    },
    {
      "index": 32,
      "text": "Must have been when I slowed down to take that curve... because for a while there, I was doing well over 100.",
      "characters": [
        "Jerry"
      ],
      "joke_types": [
        "absurdist",
        "escalation"
      ],
      "setup": "Being caught speeding at 93 mph",
      "punchline": "Claiming he was actually going faster earlier",
      "craft_total": 7.05,
      "impact_score": 7.0,
      "quotability": 6.0,
      "rewatch_bonus": 0,
      "is_callback": 0,
      "explanation": "Good absurdist escalation - making things worse when caught red-handed",
      "dialogue": [
        {
          "speaker": "Jerry",
          "line": "I was going faster before!"
        }
      ]
    },
    {
      "index": 33,
      "text": "Officer. Hi. Do you really have to give us a ticket? - All right, Nick. Let's hit it.",
      "characters": [
        "Nicki",
        "Officer",
        "Jerry"
      ],
      "joke_types": [
        "character_comedy",
        "visual_gag"
      ],
      "setup": "Nicki trying to charm the officer",
      "punchline": "Instant success without any visible effort",
      "craft_total": 7.2,
      "impact_score": 7.5,
      "quotability": 4.0,
      "rewatch_bonus": 0,
      "is_callback": 1,
      "explanation": "Excellent callback showing Nicki's power works even on authority figures",
      "dialogue": [
        {
          "speaker": "Nicki",
          "line": "Officer, I have to say, you look absolutely stunning in that uniform."
        },
        {
          "speaker": "Officer",
          "line": "Well, thank you."
        },
        {
          "speaker": "Jerry",
          "line": "She's good."
        }
      ]
    },
    {
      "index": 34,
      "text": "I didn't have enough quarters for the dryer... but this is better and more convenient. - Oh, for both of us.",
      "characters": [
        "Kramer",
        "Jerry"
      ],
      "joke_types": [
        "character_comedy",
        "irony_sarcasm"
      ],
      "setup": "Kramer using Jerry's oven to heat clothes",
      "punchline": "Jerry's sarcastic agreement about convenience",
      "craft_total": 6.55,
      "impact_score": 6.0,
      "quotability": 4.0,
      "rewatch_bonus": 0,
      "is_callback": 0,
      "explanation": "Good character moment - Jerry's dry response to Kramer's oblivious behavior",
      "dialogue": [
        {
          "speaker": "Kramer",
          "line": "I'm using your oven to heat my clothes."
        },
        {
          "speaker": "Jerry",
          "line": "Yeah, that's convenient. For you."
        }
      ]
    },
    {
      "index": 35,
      "text": "I could have got a house in Peru for 300 bucks.",
      "characters": [
        "Jerry"
      ],
      "joke_types": [
        "escalation",
        "absurdist"
      ],
      "setup": "Discovering cigars are from Peru, not Cuba",
      "punchline": "Exaggerating how cheap everything must be in Peru",
      "craft_total": 6.15,
      "impact_score": 6.0,
      "quotability": 5.0,
      "rewatch_bonus": 0,
      "is_callback": 0,
      "explanation": "Decent escalation about economic disparity but fairly predictable",
      "dialogue": [
        {
          "speaker": "Jerry",
          "line": "Peru? They're from Peru? I thought they were Cuban cigars."
        },
        {
          "speaker": "Jerry",
          "line": "Peru... So what, they're like a dollar a box down there? People are just smoking them like cigarettes?"
        },
        {
          "speaker": "Jerry",
          "line": "I bet in Peru they use them to light other cigars. 'Hey, got a light?' 'Yeah, here's a cigar.'"
        }
      ]
    },
    {
      "index": 36,
      "text": "That's a nice name, Todd Gack. What is that, Dutch?",
      "characters": [
        "Jerry"
      ],
      "joke_types": [
        "observational",
        "character_comedy"
      ],
      "setup": "Commenting on Todd's name",
      "punchline": "Guessing ethnicity from unusual surname",
      "craft_total": 5.5,
      "impact_score": 4.5,
      "quotability": 3.0,
      "rewatch_bonus": 0,
      "is_callback": 0,
      "explanation": "Minor observational humor about unusual name but not particularly funny",
      "dialogue": [
        {
          "speaker": "Jerry",
          "line": "Todd? What kind of name is Todd? It sounds like something a WASPy guy would name his son. Like, 'We're gonna call him Todd because we have no culture.'"
        }
      ]
    },
    {
      "index": 37,
      "text": "He fires people like it's a bodily function.",
      "characters": [
        "George"
      ],
      "joke_types": [
        "character_comedy",
        "absurdist"
      ],
      "setup": "George worried about Steinbrenner's reaction to no calzone",
      "punchline": "Comparing firing to involuntary biological process",
      "craft_total": 7.15,
      "impact_score": 7.0,
      "quotability": 7.5,
      "rewatch_bonus": 0,
      "is_callback": 0,
      "explanation": "Excellent metaphor that captures both Steinbrenner's impulsiveness and George's anxiety",
      "dialogue": [
        {
          "speaker": "George",
          "line": "Mr. Steinbrenner is going to fire me. He's going to come in here and fire me."
        },
        {
          "speaker": "George",
          "line": "I can feel it. It's like when you know you're going to sneeze. There's that little warning, and I've got the warning."
        },
        {
          "speaker": "George",
          "line": "I'm like one big nose hair away from getting fired."
        }
      ]
    },
    {
      "index": 38,
      "text": "No, I never had a job.",
      "characters": [
        "Jerry"
      ],
      "joke_types": [
        "deadpan_understatement",
        "character_comedy"
      ],
      "setup": "George asking about office politics",
      "punchline": "Jerry's casual admission of complete inexperience",
      "craft_total": 6.85,
      "impact_score": 6.5,
      "quotability": 6.0,
      "rewatch_bonus": 0,
      "is_callback": 0,
      "explanation": "Good character moment revealing Jerry's detachment from normal work life",
      "dialogue": [
        {
          "speaker": "George",
          "line": "So what do you do when someone at work tries to show you up?"
        },
        {
          "speaker": "Jerry",
          "line": "I don't know, I've never had a job."
        }
      ]
    },
    {
      "index": 39,
      "text": "Kramer's cooking up some corduroy.",
      "characters": [
        "Jerry"
      ],
      "joke_types": [
        "wordplay_pun",
        "absurdist"
      ],
      "setup": "Explaining smell from Kramer's clothes heating",
      "punchline": "Treating fabric like food ingredient",
      "craft_total": 6.9,
      "impact_score": 6.5,
      "quotability": 6.0,
      "rewatch_bonus": 0,
      "is_callback": 1,
      "explanation": "Clever wordplay that makes the absurd situation sound domestic and normal",
      "dialogue": [
        {
          "speaker": "Jerry",
          "line": "You can't just heat fabric like it's a food ingredient. You need to treat it with respect."
        },
        {
          "speaker": "Kramer",
          "line": "What are you talking about? It's just cloth."
        },
        {
          "speaker": "Jerry",
          "line": "Just cloth? Kramer, fabric has feelings. You're basically torturing it."
        }
      ]
    },
    {
      "index": 40,
      "text": "You hang out on the west side of the building with Seinfeld all day... just laughing it up, wasting your lives.",
      "characters": [
        "Newman"
      ],
      "joke_types": [
        "character_comedy",
        "meta_self_referential"
      ],
      "setup": "Newman explaining his dislike of George",
      "punchline": "Describing their friendship as pointless time-wasting",
      "craft_total": 6.7,
      "impact_score": 6.5,
      "quotability": 6.0,
      "rewatch_bonus": 1,
      "is_callback": 0,
      "explanation": "Good Newman moment that also functions as meta-commentary on the show itself",
      "dialogue": [
        {
          "speaker": "Newman",
          "line": "George is a bald-faced liar. He's the worst kind of friend. You know why? Because he'll never admit anything!"
        },
        {
          "speaker": "Newman",
          "line": "He just keeps piling on the lies, and he expects me to go along with it. We've known each other for years, and what do we have to show for it? Nothing! Absolutely nothing!"
        },
        {
          "speaker": "Newman",
          "line": "It's all just pointless time-wasting. That's what our friendship is."
        }
      ]
    },
    {
      "index": 41,
      "text": "And three times a week, I shall require a cannoli.",
      "characters": [
        "Newman"
      ],
      "joke_types": [
        "character_comedy",
        "escalation"
      ],
      "setup": "Newman making demands for helping George",
      "punchline": "Formal language for dessert extortion",
      "craft_total": 6.8,
      "impact_score": 6.5,
      "quotability": 6.0,
      "rewatch_bonus": 0,
      "is_callback": 0,
      "explanation": "Good Newman escalation - treating dessert demands with legal formality",
      "dialogue": [
        {
          "speaker": "Newman",
          "line": "I want the big salad."
        },
        {
          "speaker": "George",
          "line": "The big salad?"
        },
        {
          "speaker": "Newman",
          "line": "Yes. A big salad. With lots of vegetables and croutons. I want it delivered to my office by tomorrow at noon."
        },
        {
          "speaker": "George",
          "line": "Newman, that's extortion!"
        },
        {
          "speaker": "Newman",
          "line": "I prefer to think of it as a 'gratuity adjustment for services rendered.'"
        }
      ]
    },
    {
      "index": 42,
      "text": "I mean, unless I'm your sister, this is a date.",
      "characters": [
        "Elaine"
      ],
      "joke_types": [
        "observational",
        "setup_punchline"
      ],
      "setup": "Todd denying Saturday night with parents is a date",
      "punchline": "Using family relationship as only alternative explanation",
      "craft_total": 7.15,
      "impact_score": 7.0,
      "quotability": 6.5,
      "rewatch_bonus": 0,
      "is_callback": 0,
      "explanation": "Sharp logical argument that exposes the absurdity of Todd's denial",
      "dialogue": [
        {
          "speaker": "Todd",
          "line": "It's not a date. I'm just going out with my parents on Saturday night."
        },
        {
          "speaker": "Elaine",
          "line": "So what, they're just... what, they're your parents?"
        }
      ]
    },
    {
      "index": 43,
      "text": "You don't work in the rain? You're a mailman. Neither rain nor sleet nor... It's the first one!",
      "characters": [
        "George",
        "Newman"
      ],
      "joke_types": [
        "irony_sarcasm",
        "observational"
      ],
      "setup": "Newman calling in sick for rain",
      "punchline": "George citing postal service creed with Newman's contradiction",
      "craft_total": 7.6,
      "impact_score": 7.5,
      "quotability": 7.0,
      "rewatch_bonus": 0,
      "is_callback": 0,
      "explanation": "Excellent irony - Newman violates the most famous part of postal service commitment"
    },
    {
      "index": 44,
      "text": "I was never that big on creeds.",
      "characters": [
        "Newman"
      ],
      "joke_types": [
        "deadpan_understatement",
        "character_comedy"
      ],
      "setup": "George pointing out postal service creed violation",
      "punchline": "Newman's casual dismissal of professional obligations",
      "craft_total": 7.1,
      "impact_score": 7.0,
      "quotability": 7.0,
      "rewatch_bonus": 0,
      "is_callback": 0,
      "explanation": "Perfect Newman - casual dismissal of duty with philosophical pretension",
      "dialogue": [
        {
          "speaker": "George",
          "line": "Newman, you're a postal worker. Isn't there some kind of code? 'Neither snow nor rain nor heat nor gloom of night...'"
        },
        {
          "speaker": "Newman",
          "line": "Yeah, yeah, yeah. That's just something we say."
        }
      ]
    },
    {
      "index": 45,
      "text": "This is all burned up. Look at this. What the hell do I know about cooking a shirt?",
      "characters": [
        "Antonio"
      ],
      "joke_types": [
        "absurdist",
        "character_comedy"
      ],
      "setup": "Kramer's clothes heated in pizza oven",
      "punchline": "Calzone maker's confusion about clothing as food",
      "craft_total": 6.55,
      "impact_score": 6.5,
      "quotability": 5.0,
      "rewatch_bonus": 0,
      "is_callback": 1,
      "explanation": "Good payoff to clothes heating storyline with appropriate confusion",
      "dialogue": [
        {
          "speaker": "Kramer",
          "line": "My clothes are all heated up from the pizza oven."
        },
        {
          "speaker": "Pizza Place Owner",
          "line": "What? Your clothes were in my oven?"
        },
        {
          "speaker": "Kramer",
          "line": "Yeah, I needed them warmed up."
        },
        {
          "speaker": "Pizza Place Owner",
          "line": "That's a pizza oven! You can't put clothes in there!"
        },
        {
          "speaker": "Kramer",
          "line": "Why not? It's hot, isn't it?"
        },
        {
          "speaker": "Pizza Place Owner",
          "line": "It's for food! For calzones!"
        },
        {
          "speaker": "Kramer",
          "line": "Well, my clothes needed heating. What's the difference?"
        }
      ]
    },
    {
      "index": 46,
      "text": "You can't pay with this. - That's all I got. - Then you got no calzones.",
      "characters": [
        "Antonio",
        "Kramer"
      ],
      "joke_types": [
        "escalation",
        "character_comedy"
      ],
      "setup": "Kramer trying to pay with mountains of change",
      "punchline": "Escalating standoff over payment method",
      "craft_total": 6.6,
      "impact_score": 6.0,
      "quotability": 4.0,
      "rewatch_bonus": 0,
      "is_callback": 1,
      "explanation": "Good escalation that pays off Kramer's change obsession",
      "dialogue": [
        {
          "speaker": "Kramer",
          "line": "I got it all right here. Exact change."
        },
        {
          "speaker": "Cashier",
          "line": "Sir, that's... that's a lot of coins."
        },
        {
          "speaker": "Kramer",
          "line": "It's exact. Count it."
        },
        {
          "speaker": "Cashier",
          "line": "I'm not counting all that."
        },
        {
          "speaker": "Kramer",
          "line": "Well I'm not leaving until you do."
        },
        {
          "speaker": "Cashier",
          "line": "Then I guess you're not leaving."
        },
        {
          "speaker": "Kramer",
          "line": "Fine by me. I got nowhere to be."
        },
        {
          "speaker": "Manager",
          "line": "What's the problem here?"
        },
        {
          "speaker": "Kramer",
          "line": "This man won't take my money."
        },
        {
          "speaker": "Manager",
          "line": "Sir, we can't accept this much change."
        },
        {
          "speaker": "Kramer",
          "line": "It's legal tender!"
        }
      ]
    },
    {
      "index": 47,
      "text": "Your clothes smell just like Paisano's.",
      "characters": [
        "Jerry"
      ],
      "joke_types": [
        "setup_punchline",
        "observational"
      ],
      "setup": "Kramer's failed calzone mission",
      "punchline": "Clothes carrying restaurant smell from oven heating",
      "craft_total": 6.15,
      "impact_score": 5.5,
      "quotability": 4.0,
      "rewatch_bonus": 0,
      "is_callback": 0,
      "explanation": "Sets up the final plot convergence but not particularly funny on its own",
      "dialogue": [
        {
          "speaker": "Jerry",
          "line": "Your clothes smell like a calzone."
        },
        {
          "speaker": "Kramer",
          "line": "Yeah, well, I was at Poppie's all day trying to get the thing right."
        },
        {
          "speaker": "Jerry",
          "line": "Kramer, you can't just hang around a restaurant oven. You're gonna absorb the smell."
        },
        {
          "speaker": "Kramer",
          "line": "It's worth it. That calzone is gonna be perfect."
        },
        {
          "speaker": "Jerry",
          "line": "Your shirt is permanently a mozzarella stick now."
        }
      ]
    },
    {
      "index": 48,
      "text": "That smell. I know that smell. He's in the building. Costanza is in the building. And he's not in this office.",
      "characters": [
        "Steinbrenner"
      ],
      "joke_types": [
        "escalation",
        "absurdist"
      ],
      "setup": "Steinbrenner detecting calzone smell",
      "punchline": "Treating food smell like security breach with dramatic announcement",
      "craft_total": 7.25,
      "impact_score": 7.5,
      "quotability": 7.0,
      "rewatch_bonus": 1,
      "is_callback": 0,
      "explanation": "Excellent Steinbrenner moment - treating lunch absence like espionage with dramatic flair",
      "dialogue": [
        {
          "speaker": "Steinbrenner",
          "line": "What is that smell? Security! We have a breach! Someone has brought food into my office!"
        },
        {
          "speaker": "Steinbrenner",
          "line": "Lock down the building. I want every employee checked as they leave. Nobody eats in my presence without my knowledge!"
        }
      ]
    },
    {
      "index": 49,
      "text": "It's like trying to smoke a chicken bone.",
      "characters": [
        "Jerry"
      ],
      "joke_types": [
        "observational",
        "absurdist"
      ],
      "setup": "Jerry complaining about the fake Cuban cigars",
      "punchline": "Comparing cigars to inedible poultry parts",
      "craft_total": 6.7,
      "impact_score": 6.5,
      "quotability": 6.0,
      "rewatch_bonus": 0,
      "is_callback": 0,
      "explanation": "Good visceral comparison that makes the cigars sound disgusting",
      "dialogue": [
        {
          "speaker": "Jerry",
          "line": "These aren't real Cuban cigars. They're fake."
        },
        {
          "speaker": "Jerry",
          "line": "You know what fake Cuban cigars are like? They're like eating chicken feet."
        }
      ]
    },
    {
      "index": 50,
      "text": "What kind of a name is Todd Gack anyway? - I think it's Dutch.",
      "characters": [
        "Jerry",
        "Kramer"
      ],
      "joke_types": [
        "callback",
        "running_gag"
      ],
      "setup": "Jerry still puzzled by Todd's name",
      "punchline": "Kramer repeating Jerry's earlier guess",
      "craft_total": 5.1,
      "impact_score": 4.5,
      "quotability": 3.0,
      "rewatch_bonus": 0,
      "is_callback": 1,
      "explanation": "Minor callback that doesn't add much humor but provides continuity",
      "dialogue": [
        {
          "speaker": "Jerry",
          "line": "So what's his name again?"
        },
        {
          "speaker": "Kramer",
          "line": "Todd."
        },
        {
          "speaker": "Jerry",
          "line": "Todd? That's it? Just Todd?"
        },
        {
          "speaker": "Kramer",
          "line": "That's what I said when you guessed it!"
        }
      ]
    },
    {
      "index": 51,
      "text": "We'll put all the uniforms in pizza ovens before the game. That's fantastic. Keep those muscles loosey-goosey.",
      "characters": [
        "Steinbrenner"
      ],
      "joke_types": [
        "escalation",
        "character_comedy"
      ],
      "setup": "Steinbrenner learning about heated clothes",
      "punchline": "Immediately scaling idea up to entire team with sports terminology",
      "craft_total": 7.4,
      "impact_score": 7.0,
      "quotability": 6.0,
      "rewatch_bonus": 1,
      "is_callback": 0,
      "explanation": "Perfect Steinbrenner - taking random idea and immediately making it revolutionary team strategy",
      "dialogue": [
        {
          "speaker": "Steinbrenner",
          "line": "Heated clothes? That's brilliant! We'll have the entire team wearing them. Full uniform rollout by next season."
        },
        {
          "speaker": "Steinbrenner",
          "line": "I'm talking heated jerseys, heated pants, heated socks. We'll be the first team in baseball with temperature-controlled apparel."
        },
        {
          "speaker": "Steinbrenner",
          "line": "The Yankees will never be cold again. We'll dominate every game, every season. This is it. This is how we win."
        }
      ]
    },
    {
      "index": 52,
      "text": "I smell a pennant!",
      "characters": [
        "Steinbrenner"
      ],
      "joke_types": [
        "wordplay_pun",
        "escalation"
      ],
      "setup": "Steinbrenner excited about heated uniforms",
      "punchline": "Playing on 'smell' from clothes to predicting championship",
      "craft_total": 6.95,
      "impact_score": 6.5,
      "quotability": 7.0,
      "rewatch_bonus": 0,
      "is_callback": 0,
      "explanation": "Good closing line that uses smell motif to predict baseball success - classic Steinbrenner optimism",
      "dialogue": [
        {
          "speaker": "Steinbrenner",
          "line": "I'm telling you, these heated uniforms are going to revolutionize baseball. Our players will be warm, comfortable, and ready to win!"
        },
        {
          "speaker": "Steinbrenner",
          "line": "You know what? I can already smell the championship."
        },
        {
          "speaker": "George",
          "line": "Mr. Steinbrenner, that's just the uniforms burning."
        }
      ]
    }
  ],
  "air_date": "1996-04-04",
  "imdb_rating": 8.7,
  "imdb_votes": 4511,
  "tmdb_overview": "Jerry gets miffed when a salesman hits on Elaine while she's with him; George suspects hookers are conducting business in his parked car.",
  "still_path": "/i2LAvCheRR0E1XirVACc2y3KOM7.jpg",
  "director": [
    "Andy Ackerman"
  ],
  "writers": [
    "Spike Feresten"
  ],
  "guest_stars": [
    {
      "name": "Harry Van Gorkum",
      "character": "Craig",
      "profile_path": "/6MQ31z3ewX4KTHdMMze8SIZ19PU.jpg"
    },
    {
      "name": "Michael McDonald",
      "character": "Jesse",
      "profile_path": "/mIsG6qOHvvID2mQL2GOY1ONPHHV.jpg"
    },
    {
      "name": "Patrick Bristow",
      "character": "Wig Master",
      "profile_path": "/bNnv5c0AyJdfI5kYhucARYvqm9F.jpg"
    },
    {
      "name": "Gina Mastrogiacomo",
      "character": "Prostitute",
      "profile_path": "/wB21RlcvbONf8UD5CzJ9MLoZIVJ.jpg"
    },
    {
      "name": "Pamela Dillman",
      "character": "Salesperson",
      "profile_path": null
    },
    {
      "name": "Heidi Swedberg",
      "character": "Susan Ross",
      "profile_path": "/aDMeu2mOXgCYOXEr3U795BYpl7t.jpg"
    },
    {
      "name": "Kim Chase",
      "character": "Charmaine",
      "profile_path": "/z33rBqterW1ryQ43TqCwrH32qKB.jpg"
    },
    {
      "name": "Chaim Jeraffi",
      "character": "Jiffy Park Guy",
      "profile_path": "/odxOLYdm8mOihxpkWzNI1FMdU1I.jpg"
    }
  ],
  "insight": "Underwhelming density (2.23 JPM) drags an otherwise character-driven episode below Seinfeld's standards."
}