{
  "show": "Parks and Recreation",
  "slug": "parks-and-recreation",
  "season": 6,
  "episode_number": 17,
  "title": "Galentines Day",
  "humor_index": 73.1,
  "jpm": 2.89,
  "avg_craft": 6.87,
  "avg_impact": 6.43,
  "total_jokes": 81,
  "dominant_joke_types": "[\"character_comedy\", \"absurdist\", \"cringe_discomfort\"]",
  "standout_joke_ids": "[43, 32, 75]",
  "weakest_section": null,
  "jokes": [
    {
      "index": 1,
      "text": "The only thing I am crazy about is a magnificent, pregnant manta ray named Ann Perkins.",
      "characters": [
        "Chris"
      ],
      "joke_types": [
        "character_comedy",
        "absurdist"
      ],
      "setup": "Someone calls Chris crazy",
      "punchline": "Chris responds with an elaborate, over-the-top metaphor comparing Ann to a pregnant manta ray",
      "craft_total": 7.17,
      "impact_score": 6.5,
      "quotability": 7.0,
      "rewatch_bonus": 1,
      "is_callback": 0,
      "explanation": "Perfect Chris Traeger character moment - his overly enthusiastic, poetic language applied to something mundane. The manta ray comparison is both unexpected and weirdly beautiful."
    },
    {
      "index": 2,
      "text": "I am ranking topics of conversation for our next phone call... Infinity scarves or whether or not it's worth it for me to get Showtime?",
      "characters": [
        "Leslie"
      ],
      "joke_types": [
        "character_comedy",
        "observational"
      ],
      "setup": "Leslie mentions ranking conversation topics",
      "punchline": "The absurd specificity and mundane nature of the topics she's prioritizing",
      "craft_total": 6.13,
      "impact_score": 5.33,
      "quotability": 5.0,
      "rewatch_bonus": 0,
      "is_callback": 0,
      "explanation": "Classic Leslie overthinking - turning casual conversation into a ranked priority system with hilariously trivial topics."
    },
    {
      "index": 3,
      "text": "I mean, I can talk about Sandra Bullock skirt length.",
      "characters": [
        "Ben"
      ],
      "joke_types": [
        "character_comedy",
        "irony_sarcasm"
      ],
      "setup": "Ben offers to be a sounding board for female topics",
      "punchline": "His awkward, masculine attempt to relate results in a weirdly specific and inappropriate topic",
      "craft_total": 6.75,
      "impact_score": 6.0,
      "quotability": 6.5,
      "rewatch_bonus": 0,
      "is_callback": 0,
      "explanation": "Ben's sincere but completely tone-deaf attempt to connect with female conversation topics. The specificity of 'Sandra Bullock skirt length' is perfectly awkward."
    },
    {
      "index": 4,
      "text": "No, no, babe, you can't--you would just embarrass yourself. Plus, every time I start talking to you, five seconds later, I want to jump your bones.",
      "characters": [
        "Leslie"
      ],
      "joke_types": [
        "character_comedy",
        "cringe_discomfort"
      ],
      "setup": "Ben offers to help with girl talk",
      "punchline": "Leslie's blunt rejection followed by her oversharing about their sex life",
      "craft_total": 6.23,
      "impact_score": 5.83,
      "quotability": 4.5,
      "rewatch_bonus": 0,
      "is_callback": 0,
      "explanation": "Leslie's characteristic oversharing and directness. The transition from dismissal to TMI is appropriately awkward."
    },
    {
      "index": 5,
      "text": "I love being a father, but there are a few things I miss. Silence, the absence of noise, one single moment undisturbed by the sounds of a children's TV program called Doc McStuffins.",
      "characters": [
        "Ron"
      ],
      "joke_types": [
        "observational",
        "character_comedy"
      ],
      "setup": "Ron talks about missing things as a father",
      "punchline": "His poetic description of missing silence, undercut by the specific annoyance of Doc McStuffins",
      "craft_total": 6.9,
      "impact_score": 6.83,
      "quotability": 7.5,
      "rewatch_bonus": 1,
      "is_callback": 0,
      "explanation": "Perfect Ron Swanson - his philosophical, almost poetic language applied to the mundane frustrations of parenthood. The specificity of Doc McStuffins grounds it in reality."
    },
    {
      "index": 6,
      "text": "There is no quiet anymore. There is only Doc McStuffins.",
      "characters": [
        "Ron"
      ],
      "joke_types": [
        "deadpan_understatement",
        "character_comedy"
      ],
      "setup": "Ron's continued lament about noise",
      "punchline": "The dramatic finality of 'There is only Doc McStuffins' delivered in Ron's deadpan style",
      "craft_total": 7.3,
      "impact_score": 7.33,
      "quotability": 8.5,
      "rewatch_bonus": 1,
      "is_callback": 0,
      "explanation": "Brilliantly economical and quotable. Ron's existential despair expressed through a children's TV show creates perfect comedic contrast."
    },
    {
      "index": 7,
      "text": "Shotgun! I call shotgun. Where are we going? Doesn't matter. Shotgun. Shotgun on all rides for the rest of the day. For the rest of my life. In any car! Ha ha! I just faced you suckers!",
      "characters": [
        "Andy"
      ],
      "joke_types": [
        "character_comedy",
        "escalation"
      ],
      "setup": "Andy volunteers to go with Ron",
      "punchline": "His childish excitement escalating to claiming shotgun for life in any car",
      "craft_total": 6.33,
      "impact_score": 6.33,
      "quotability": 5.5,
      "rewatch_bonus": 0,
      "is_callback": 0,
      "explanation": "Pure Andy Dwyer - his childlike enthusiasm and inability to understand boundaries. The escalation from one car ride to 'all cars for life' is perfectly in character."
    },
    {
      "index": 8,
      "text": "Is the tent guy left-handed or right-handed? I just need to know which way to part my hair to get us a better price. It's a business theory I'm working on.",
      "characters": [
        "Tom"
      ],
      "joke_types": [
        "character_comedy",
        "absurdist"
      ],
      "setup": "Tom asks about the tent guy's handedness",
      "punchline": "The ridiculous connection between hair parting direction and business negotiations",
      "craft_total": 7.3,
      "impact_score": 6.83,
      "quotability": 6.5,
      "rewatch_bonus": 1,
      "is_callback": 0,
      "explanation": "Perfect Tom Haverford - his pseudo-sophisticated business theories that are completely absurd. The specificity of the hair parting makes it memorable."
    },
    {
      "index": 9,
      "text": "A straightforward deal? Why didn't you tell me? I don't have my straightforward deal fedora on me. We gotta stop by my storage unit on the way up.",
      "characters": [
        "Tom"
      ],
      "joke_types": [
        "character_comedy",
        "absurdist"
      ],
      "setup": "Ben mentions it's a straightforward deal",
      "punchline": "Tom's implication that he has different hats for different types of business deals",
      "craft_total": 7.07,
      "impact_score": 6.67,
      "quotability": 7.5,
      "rewatch_bonus": 1,
      "is_callback": 0,
      "explanation": "Excellent character work - Tom's ridiculous over-preparation and the idea of having specialized fedoras for different business scenarios is perfectly absurd."
    },
    {
      "index": 10,
      "text": "Remember you said that when Larry's farting up the car.",
      "characters": [
        "Tom"
      ],
      "joke_types": [
        "character_comedy",
        "cringe_discomfort"
      ],
      "setup": "Ben defends inviting Larry",
      "punchline": "Tom's crude but probably accurate prediction about Larry",
      "craft_total": 5.3,
      "impact_score": 4.75,
      "quotability": 4.0,
      "rewatch_bonus": 0,
      "is_callback": 0,
      "explanation": "Standard Larry mockery - functional but not particularly creative. Gets the job done with basic physical humor."
    },
    {
      "index": 11,
      "text": "Larry isn't that bad. He's nice. And frankly, I don't care who knows that I said that, as long as no one knows that I said that.",
      "characters": [
        "Ben"
      ],
      "joke_types": [
        "irony_sarcasm",
        "character_comedy"
      ],
      "setup": "Ben defends Larry",
      "punchline": "The immediate contradiction of saying he doesn't care who knows while immediately caring who knows",
      "craft_total": 7.07,
      "impact_score": 6.67,
      "quotability": 7.0,
      "rewatch_bonus": 0,
      "is_callback": 0,
      "explanation": "Nice logical contradiction delivered with perfect timing. Shows Ben's awareness of the social dynamics while still wanting to be kind."
    },
    {
      "index": 12,
      "text": "Listen to me very carefully. I have not been taken. I know that's always your first fear when I'm not available, but this is not a Liam Neeson Taken scenario.",
      "characters": [
        "Ann"
      ],
      "joke_types": [
        "callback",
        "character_comedy"
      ],
      "setup": "Ann leaving a voicemail explaining her absence",
      "punchline": "Her knowledge that Leslie immediately assumes kidnapping scenarios",
      "craft_total": 6.93,
      "impact_score": 6.67,
      "quotability": 6.5,
      "rewatch_bonus": 1,
      "is_callback": 1,
      "explanation": "Great character moment showing how well Ann knows Leslie's paranoid tendencies. The Taken reference is specific and relatable."
    },
    {
      "index": 13,
      "text": "That's exactly what they'd make you say. Also, no one's making me say this. I am a free woman, untaken, simply going about my business.",
      "characters": [
        "Ann"
      ],
      "joke_types": [
        "escalation",
        "character_comedy"
      ],
      "setup": "Ann's denial of being taken",
      "punchline": "Her continued denials that sound increasingly like what a kidnapped person would say",
      "craft_total": 6.63,
      "impact_score": 6.17,
      "quotability": 5.5,
      "rewatch_bonus": 0,
      "is_callback": 0,
      "explanation": "Good follow-up to the kidnapping joke. Ann's awareness of how suspicious her denials sound creates nice meta-humor."
    },
    {
      "index": 14,
      "text": "What's good, baby? What's going down in Donna town? What's the haps in Meagle-wood?",
      "characters": [
        "Leslie"
      ],
      "joke_types": [
        "character_comedy",
        "cringe_discomfort"
      ],
      "setup": "Leslie trying to bond with Donna",
      "punchline": "Her awkward, try-hard slang that sounds forced and unnatural",
      "craft_total": 6.13,
      "impact_score": 5.67,
      "quotability": 5.0,
      "rewatch_bonus": 0,
      "is_callback": 0,
      "explanation": "Leslie trying too hard to sound cool with forced slang. The 'Meagle-wood' portmanteau is particularly cringeworthy in a good way."
    },
    {
      "index": 15,
      "text": "I'm listening to Jaleel Or No Deal. It's a podcast where the kid who played Urkel reviews old Deal Or No Deal episodes. It's pointless, and I love it.",
      "characters": [
        "Donna"
      ],
      "joke_types": [
        "absurdist",
        "character_comedy"
      ],
      "setup": "Donna explaining what she's listening to",
      "punchline": "The absurdly specific and pointless nature of this fictional podcast",
      "craft_total": 7.43,
      "impact_score": 7.5,
      "quotability": 8.0,
      "rewatch_bonus": 1,
      "is_callback": 0,
      "explanation": "Brilliant absurdist concept - the specificity of combining Jaleel White with Deal or No Deal is perfectly random yet somehow believable. Donna's honest assessment makes it funnier."
    },
    {
      "index": 16,
      "text": "What's the 411, little mama? What's the hot goss? Who you crushing on these days?",
      "characters": [
        "Leslie"
      ],
      "joke_types": [
        "character_comedy",
        "cringe_discomfort"
      ],
      "setup": "Leslie continuing her forced slang with April",
      "punchline": "The cringey outdated slang getting progressively worse",
      "craft_total": 6.2,
      "impact_score": 5.83,
      "quotability": 4.5,
      "rewatch_bonus": 0,
      "is_callback": 0,
      "explanation": "Continuation of Leslie's awkward slang attempts. The escalation to 'little mama' and 'hot goss' makes it appropriately uncomfortable."
    },
    {
      "index": 17,
      "text": "Ew, my husband, weirdo. Can I get back to work now? Thanks. Bye.",
      "characters": [
        "April"
      ],
      "joke_types": [
        "deadpan_understatement",
        "character_comedy"
      ],
      "setup": "Leslie asks who April is crushing on",
      "punchline": "April's disgusted reaction to the question and dismissive shutdown",
      "craft_total": 7.2,
      "impact_score": 6.5,
      "quotability": 6.0,
      "rewatch_bonus": 0,
      "is_callback": 0,
      "explanation": "Perfect April response - simultaneously answering the question while expressing complete disdain for the interaction. The quick dismissal is efficiently brutal."
    },
    {
      "index": 18,
      "text": "You sound like a tampon commercial.",
      "characters": [
        "April"
      ],
      "joke_types": [
        "deadpan_understatement",
        "character_comedy"
      ],
      "setup": "Leslie talks about 'lady time'",
      "punchline": "April's blunt, accurate observation about Leslie's language",
      "craft_total": 7.0,
      "impact_score": 6.67,
      "quotability": 7.5,
      "rewatch_bonus": 0,
      "is_callback": 0,
      "explanation": "Perfectly delivered April line - cutting through Leslie's enthusiasm with brutal honesty. The comparison is unexpected but spot-on."
    },
    {
      "index": 19,
      "text": "Wait, I thought you weren't gonna do Galentine's day this year because that she-beast moved away. I believe her name was Satan?",
      "characters": [
        "April"
      ],
      "joke_types": [
        "deadpan_understatement",
        "character_comedy"
      ],
      "setup": "April commenting on Leslie's Galentine's Day plans",
      "punchline": "Her casual reference to Ann as 'she-beast' and 'Satan'",
      "craft_total": 6.87,
      "impact_score": 6.33,
      "quotability": 6.5,
      "rewatch_bonus": 0,
      "is_callback": 0,
      "explanation": "Classic April - her dislike of Ann expressed through casual cruelty delivered in deadpan style. The escalation from 'she-beast' to 'Satan' works well."
    },
    {
      "index": 20,
      "text": "Side note, do not Google that phrase.",
      "characters": [
        "Leslie"
      ],
      "joke_types": [
        "meta_self_referential",
        "innuendo"
      ],
      "setup": "Leslie mentions 'women's-only marathon bonding session with tons of whipped cream'",
      "punchline": "Her awareness of how that phrase could be interpreted online",
      "craft_total": 6.57,
      "impact_score": 6.5,
      "quotability": 6.5,
      "rewatch_bonus": 0,
      "is_callback": 0,
      "explanation": "Meta joke acknowledging the unintended sexual implications of her innocent description. Leslie's awareness makes it funnier."
    },
    {
      "index": 21,
      "text": "Do you know what my social security number is? Or if I'm allergic to anything? I don't like corn. Should I put that down? Or will that be confusing? Because I do like candy corn.",
      "characters": [
        "Andy"
      ],
      "joke_types": [
        "character_comedy",
        "absurdist"
      ],
      "setup": "Andy needing medical information",
      "punchline": "His confusion about corn vs candy corn as an allergy",
      "craft_total": 6.63,
      "impact_score": 6.33,
      "quotability": 5.5,
      "rewatch_bonus": 0,
      "is_callback": 0,
      "explanation": "Pure Andy logic - treating a food preference as a medical allergy and being confused by the corn/candy corn distinction. Perfectly childlike reasoning."
    },
    {
      "index": 22,
      "text": "Ron, look. I found all three differences. Those are two completely different pictures.",
      "characters": [
        "Andy",
        "Ron"
      ],
      "joke_types": [
        "character_comedy",
        "visual_gag"
      ],
      "setup": "Andy claiming to find differences in pictures",
      "punchline": "Ron's deadpan observation that they're completely different pictures",
      "craft_total": 7.33,
      "impact_score": 7.0,
      "quotability": 7.0,
      "rewatch_bonus": 1,
      "is_callback": 0,
      "explanation": "Perfect character interaction - Andy's misunderstanding of the game met with Ron's matter-of-fact correction. The absurdity is grounded in character."
    },
    {
      "index": 23,
      "text": "Oh, whoa. Five-second rule. No, ahh. Come on, we better get you to a dentist.",
      "characters": [
        "Andy",
        "Ron"
      ],
      "joke_types": [
        "physical_slapstick",
        "character_comedy"
      ],
      "setup": "Andy hurts his tooth",
      "punchline": "His attempt to apply the five-second rule to a dental injury",
      "craft_total": 6.23,
      "impact_score": 5.67,
      "quotability": 5.0,
      "rewatch_bonus": 0,
      "is_callback": 0,
      "explanation": "Andy's illogical application of food rules to dental trauma. Shows his childlike thinking process under stress."
    },
    {
      "index": 24,
      "text": "Oh, my God, Larry. Your tuna fish sandwich stunk up my suit. Gayle made it for me. Irrelevant.",
      "characters": [
        "Tom",
        "Larry"
      ],
      "joke_types": [
        "character_comedy",
        "cringe_discomfort"
      ],
      "setup": "Tom complaining about Larry's sandwich smell",
      "punchline": "Tom's dismissal of Larry's innocent explanation",
      "craft_total": 5.63,
      "impact_score": 4.83,
      "quotability": 4.5,
      "rewatch_bonus": 0,
      "is_callback": 0,
      "explanation": "Standard Larry harassment - Tom's superficial concerns vs Larry's simple explanations. The 'irrelevant' dismissal is characteristically cruel."
    },
    {
      "index": 25,
      "text": "Who's this little genie right here?",
      "characters": [
        "Harvey"
      ],
      "joke_types": [
        "visual_gag",
        "character_comedy"
      ],
      "setup": "Harvey meeting Tom at the tent store",
      "punchline": "The tent guy's assessment of Tom as a 'little genie'",
      "craft_total": 6.15,
      "impact_score": 5.5,
      "quotability": 6.0,
      "rewatch_bonus": 0,
      "is_callback": 0,
      "explanation": "Good visual/character humor about Tom's appearance and demeanor"
    },
    {
      "index": 26,
      "text": "I got over 1,300 tents in this warehouse alone. 900 of those are over 2,000 square feet, 80 of 'em are striped, and exactly 4 of 'em were once rented by Miss Rene Russo.",
      "characters": [
        "Harvey"
      ],
      "joke_types": [
        "character_comedy",
        "absurdist"
      ],
      "setup": "Harvey describing his tent expertise",
      "punchline": "The oddly specific statistics ending with the random Rene Russo detail",
      "craft_total": 7.03,
      "impact_score": 6.67,
      "quotability": 7.5,
      "rewatch_bonus": 1,
      "is_callback": 0,
      "explanation": "Great character establishment - Harvey's obsessive knowledge combined with the random celebrity detail shows he's both professional and eccentric."
    },
    {
      "index": 27,
      "text": "I was gonna go with my boyfriend, but he couldn't come because he decided to stay with his wife.",
      "characters": [
        "Shauna"
      ],
      "joke_types": [
        "dark_subversive",
        "cringe_discomfort"
      ],
      "setup": "Shauna talking about her solo trip to Rome",
      "punchline": "The casual revelation that her boyfriend is married",
      "craft_total": 7.13,
      "impact_score": 7.0,
      "quotability": 6.5,
      "rewatch_bonus": 0,
      "is_callback": 0,
      "explanation": "Dark humor delivered casually - Shauna's matter-of-fact revelation of being the other woman. The casual tone makes it more uncomfortable."
    },
    {
      "index": 28,
      "text": "Rome's played out. Have y'all been to Kuala Lumpur? I go all the time. Where do you think I got that crystal Buddha head above my jacuzzi?",
      "characters": [
        "Donna"
      ],
      "joke_types": [
        "character_comedy",
        "one_upmanship"
      ],
      "setup": "Shauna mentioning Rome",
      "punchline": "Donna's casual one-upmanship with exotic travel and luxury details",
      "craft_total": 6.97,
      "impact_score": 6.33,
      "quotability": 6.0,
      "rewatch_bonus": 0,
      "is_callback": 0,
      "explanation": "Perfect Donna - effortlessly outdoing someone while revealing her luxurious lifestyle. The Buddha head detail adds character specificity."
    },
    {
      "index": 29,
      "text": "And then we got Evelyn, aka fake Ann. I don't know her last name. Honestly we just needed bodies.",
      "characters": [
        "Leslie"
      ],
      "joke_types": [
        "character_comedy",
        "cringe_discomfort"
      ],
      "setup": "Leslie introducing the Galentine's Day candidates",
      "punchline": "Her brutally honest assessment of Evelyn as just a warm body",
      "craft_total": 6.93,
      "impact_score": 6.5,
      "quotability": 6.5,
      "rewatch_bonus": 0,
      "is_callback": 0,
      "explanation": "Leslie's characteristic over-honesty combined with her desperation to fill the Ann void. The 'fake Ann' nickname is particularly harsh."
    },
    {
      "index": 30,
      "text": "But please answer them with complete honesty 'cause I'll be able to tell if you're lying.",
      "characters": [
        "Leslie"
      ],
      "joke_types": [
        "character_comedy",
        "setup_punchline"
      ],
      "setup": "Leslie introducing the Q&A as 'just for fun'",
      "punchline": "Immediately revealing it's actually a serious test with lie detection",
      "craft_total": 6.9,
      "impact_score": 6.25,
      "quotability": 6.0,
      "rewatch_bonus": 0,
      "is_callback": 0,
      "explanation": "Good character moment showing Leslie's intensity disguised as casual fun"
    },
    {
      "index": 31,
      "text": "Well, for live tweeting, it's Scandal. For binge watching, it's Scandal. But for fashion, it's actually Scandal. My answer is Scandal.",
      "characters": [
        "Donna"
      ],
      "joke_types": [
        "escalation",
        "character_comedy"
      ],
      "setup": "Leslie asks about favorite TV show",
      "punchline": "Donna's elaborate breakdown that all leads to the same answer",
      "craft_total": 7.1,
      "impact_score": 6.67,
      "quotability": 6.0,
      "rewatch_bonus": 0,
      "is_callback": 0,
      "explanation": "Good structure - building expectation of variety before revealing it's all the same show. Shows Donna's sophistication and obsession."
    },
    {
      "index": 32,
      "text": "Ooh, I love watching Russian traffic accidents on YouTube while I play children's music at the wrong RPM.",
      "characters": [
        "April"
      ],
      "joke_types": [
        "dark_subversive",
        "character_comedy"
      ],
      "setup": "April asked about her favorite TV show",
      "punchline": "Her disturbing combination of violent content with corrupted children's music",
      "craft_total": 8.03,
      "impact_score": 7.83,
      "quotability": 8.5,
      "rewatch_bonus": 1,
      "is_callback": 0,
      "explanation": "Perfectly April - dark, specific, and weirdly artistic. The combination of Russian dash cam footage with slowed children's music is brilliantly disturbing and creative."
    },
    {
      "index": 33,
      "text": "I like beauty pageants. Everyone is so happy and perfect.",
      "characters": [
        "Shauna"
      ],
      "joke_types": [
        "character_comedy",
        "irony_sarcasm"
      ],
      "setup": "Shauna sharing her TV preferences",
      "punchline": "The ironic contrast between her messy life and attraction to perfection",
      "craft_total": 6.77,
      "impact_score": 6.17,
      "quotability": 4.5,
      "rewatch_bonus": 0,
      "is_callback": 0,
      "explanation": "Good character insight - Shauna's attraction to artificial perfection contrasts with her complicated personal life. Shows her escapist tendencies."
    },
    {
      "index": 34,
      "text": "I like Diagnosis Murder. And skin flicks.",
      "characters": [
        "Ethel"
      ],
      "joke_types": [
        "character_comedy",
        "shock_humor"
      ],
      "setup": "Ethel sharing her TV preferences",
      "punchline": "The unexpected combination of a wholesome medical show with adult films",
      "craft_total": 7.37,
      "impact_score": 7.33,
      "quotability": 7.5,
      "rewatch_bonus": 1,
      "is_callback": 0,
      "explanation": "Perfect subversion - the sweet elderly lady casually mentioning adult content alongside Dick Van Dyke. The economy and shock value work perfectly."
    },
    {
      "index": 35,
      "text": "The correct answer for favorite TV show is Friday Night Lights.",
      "characters": [
        "Leslie"
      ],
      "joke_types": [
        "character_comedy",
        "cringe_discomfort"
      ],
      "setup": "After hearing everyone's TV preferences",
      "punchline": "Leslie's declaration that there's only one correct answer",
      "craft_total": 6.97,
      "impact_score": 6.5,
      "quotability": 5.5,
      "rewatch_bonus": 0,
      "is_callback": 0,
      "explanation": "Classic Leslie - treating subjective preferences as objective facts. Shows her controlling nature in friendship evaluation."
    },
    {
      "index": 36,
      "text": "The correct answer for favorite TV show is Friday Night Lights.",
      "characters": [
        "Leslie"
      ],
      "joke_types": [
        "character_comedy",
        "setup_punchline"
      ],
      "setup": "Everyone giving different TV show answers",
      "punchline": "Leslie revealing there was actually only one correct answer",
      "craft_total": 7.1,
      "impact_score": 6.5,
      "quotability": 6.5,
      "rewatch_bonus": 0,
      "is_callback": 0,
      "explanation": "Perfect Leslie moment showing her controlling nature and predetermined answers"
    },
    {
      "index": 37,
      "text": "Well, you need flaps, bro. A tent without flaps is basically a parachute.",
      "characters": [
        "Harvey"
      ],
      "joke_types": [
        "character_comedy",
        "absurdist"
      ],
      "setup": "Ben questioning the flap tax",
      "punchline": "Harvey's oddly compelling but ridiculous tent philosophy",
      "craft_total": 7.23,
      "impact_score": 6.83,
      "quotability": 8.0,
      "rewatch_bonus": 1,
      "is_callback": 0,
      "explanation": "Great absurdist logic - Harvey's passionate tent expertise creates a weirdly convincing but ridiculous argument. The parachute comparison is memorably bizarre."
    },
    {
      "index": 38,
      "text": "Shh. Keep your voice down, please, there's tents here.",
      "characters": [
        "Harvey"
      ],
      "joke_types": [
        "character_comedy",
        "absurdist"
      ],
      "setup": "Ben raising his voice about tent costs",
      "punchline": "Harvey treating tents like they can be damaged by loud voices",
      "craft_total": 7.77,
      "impact_score": 7.33,
      "quotability": 8.0,
      "rewatch_bonus": 1,
      "is_callback": 0,
      "explanation": "Brilliant character moment - Harvey's reverence for tents extends to protecting them from noise. The absurdity is delivered with complete sincerity."
    },
    {
      "index": 39,
      "text": "Now, look, you can argue with me all you want, but for every line item that you two idiots disagree with, there's gonna be a $50 discussion surcharge.",
      "characters": [
        "Harvey"
      ],
      "joke_types": [
        "character_comedy",
        "escalation"
      ],
      "setup": "Ben and Tom questioning the contract",
      "punchline": "Harvey charging them for the act of questioning charges",
      "craft_total": 7.23,
      "impact_score": 7.0,
      "quotability": 7.0,
      "rewatch_bonus": 1,
      "is_callback": 0,
      "explanation": "Excellent escalation - Harvey's absurd business practices reach peak ridiculousness. The meta-charge for questioning charges is brilliantly circular."
    },
    {
      "index": 40,
      "text": "What's the price now? $80 more. I liked it better the other way. Does have an effect, though.",
      "characters": [
        "Tom",
        "Harvey"
      ],
      "joke_types": [
        "character_comedy",
        "visual_gag"
      ],
      "setup": "Tom tries his hair-parting business theory",
      "punchline": "It actually has an effect but makes things worse",
      "craft_total": 6.9,
      "impact_score": 6.33,
      "quotability": 5.5,
      "rewatch_bonus": 1,
      "is_callback": 1,
      "explanation": "Nice callback to Tom's earlier absurd theory, with the twist that it works but backfires. Shows the writers thought through the setup."
    },
    {
      "index": 41,
      "text": "Do you know what my social security number is? Or if I'm allergic to anything? I don't like corn. Should I put that down? Or will that be confusing? Because I do like candy corn.",
      "characters": [
        "Andy"
      ],
      "joke_types": [
        "character_comedy",
        "absurdist"
      ],
      "setup": "Andy at the dentist office",
      "punchline": "His continued confusion about basic medical forms and corn logic",
      "craft_total": 6.53,
      "impact_score": 5.83,
      "quotability": 5.0,
      "rewatch_bonus": 0,
      "is_callback": 1,
      "explanation": "Callback to earlier corn confusion, but feels somewhat repetitive. Still works as character consistency but less fresh."
    },
    {
      "index": 42,
      "text": "All I wanted was two hours where I got to forget that I was a parent.",
      "characters": [
        "Ron"
      ],
      "joke_types": [
        "character_comedy",
        "observational"
      ],
      "setup": "Ron dealing with Andy's childish behavior",
      "punchline": "His realization that he's basically babysitting another child",
      "craft_total": 7.07,
      "impact_score": 6.83,
      "quotability": 7.0,
      "rewatch_bonus": 1,
      "is_callback": 0,
      "explanation": "Perfect character moment - Ron's desire for escape from parenting responsibilities met with Andy's childlike neediness. The irony is beautifully constructed."
    },
    {
      "index": 43,
      "text": "I've gotten two annulments. One for pleasure, and one to cap off a long con I was running against Keith Sweat.",
      "characters": [
        "Donna"
      ],
      "joke_types": [
        "character_comedy",
        "dark_subversive"
      ],
      "setup": "Donna sharing something personal during Q&A",
      "punchline": "The casually mentioned criminal activity against a R&B singer",
      "craft_total": 7.97,
      "impact_score": 8.17,
      "quotability": 9.0,
      "rewatch_bonus": 1,
      "is_callback": 0,
      "explanation": "Brilliant Donna moment - the casual revelation of conning Keith Sweat is so specific and unexpected. The 'for pleasure' vs criminal motivation split is perfectly absurd."
    },
    {
      "index": 44,
      "text": "I'm writing a memoir based on my blog. It's called Tweeping Up Appearances, and it's about my journey to find happiness by smiling through the pain.",
      "characters": [
        "Shauna"
      ],
      "joke_types": [
        "character_comedy",
        "wordplay_pun"
      ],
      "setup": "Shauna sharing her writing project",
      "punchline": "The terrible pun title that perfectly captures her shallow optimism",
      "craft_total": 6.6,
      "impact_score": 5.83,
      "quotability": 6.5,
      "rewatch_bonus": 0,
      "is_callback": 0,
      "explanation": "Good character work - the terrible pun title reflects Shauna's superficial approach to serious topics. Shows her lack of self-awareness."
    },
    {
      "index": 45,
      "text": "It's simply a way for me to figure out which one of you is the best.",
      "characters": [
        "Leslie"
      ],
      "joke_types": [
        "character_comedy",
        "cringe_discomfort"
      ],
      "setup": "Leslie caught with friendship rankings",
      "punchline": "Her honest admission of the ranking's purpose",
      "craft_total": 6.67,
      "impact_score": 6.17,
      "quotability": 6.0,
      "rewatch_bonus": 0,
      "is_callback": 0,
      "explanation": "Classic Leslie - her inability to lie or sugarcoat creates maximum social damage. The directness makes it funnier and more uncomfortable."
    },
    {
      "index": 46,
      "text": "According to her, it's the best view.",
      "characters": [
        "Larry"
      ],
      "joke_types": [
        "character_comedy",
        "innuendo"
      ],
      "setup": "Larry explaining Gayle watching him clean windshields",
      "punchline": "The unintentional sexual implication of Gayle's perspective",
      "craft_total": 6.73,
      "impact_score": 6.67,
      "quotability": 5.0,
      "rewatch_bonus": 0,
      "is_callback": 0,
      "explanation": "Innocent Larry inadvertently creating sexual innuendo through his description of Gayle's behavior. Works through Larry's obliviousness."
    },
    {
      "index": 47,
      "text": "Gayle always has me do the windshield. She likes to stand behind me and watch. According to her, it's the best view.",
      "characters": [
        "Larry"
      ],
      "joke_types": [
        "character_comedy",
        "observational"
      ],
      "setup": "Larry washing windshield and being nice",
      "punchline": "The sweet but awkward detail about Gayle watching him",
      "craft_total": 6.93,
      "impact_score": 6.5,
      "quotability": 5.5,
      "rewatch_bonus": 0,
      "is_callback": 0,
      "explanation": "Sweet character moment showing Larry and Gayle's relationship dynamic"
    },
    {
      "index": 48,
      "text": "I'm sorry. I'm just not used to people from the office asking me things. It's kind of scary. But in a good way, though.",
      "characters": [
        "Larry"
      ],
      "joke_types": [
        "character_comedy",
        "cringe_discomfort"
      ],
      "setup": "Ben showing genuine interest in Larry's family",
      "punchline": "Larry's pathetic gratitude for basic human interaction",
      "craft_total": 6.7,
      "impact_score": 6.33,
      "quotability": 5.5,
      "rewatch_bonus": 1,
      "is_callback": 0,
      "explanation": "Genuinely sad moment that's also funny - Larry's surprise at being treated like a human being. Shows how badly he's usually treated."
    },
    {
      "index": 49,
      "text": "Yeah. Yeah, it was loud. Smells like a hippopotamus took a dump on a skunk.",
      "characters": [
        "Larry"
      ],
      "joke_types": [
        "character_comedy",
        "setup_punchline"
      ],
      "setup": "Larry covering for Ben's kindness by claiming he farted",
      "punchline": "His surprisingly vivid and elaborate description of the fictional fart",
      "craft_total": 6.6,
      "impact_score": 6.0,
      "quotability": 7.0,
      "rewatch_bonus": 0,
      "is_callback": 0,
      "explanation": "Larry protecting Ben's reputation by embellishing the fart story. The animal comparison is surprisingly creative and specific."
    },
    {
      "index": 50,
      "text": "Well, my grandmother was missing that tooth, and she was the most beautiful woman on her oil rig.",
      "characters": [
        "Andy"
      ],
      "joke_types": [
        "character_comedy",
        "absurdist"
      ],
      "setup": "Andy explaining why his missing tooth looks fine",
      "punchline": "The casual revelation about his grandmother working on an oil rig",
      "craft_total": 7.13,
      "impact_score": 6.67,
      "quotability": 7.5,
      "rewatch_bonus": 1,
      "is_callback": 0,
      "explanation": "Perfect Andy logic - the unexpected detail about grandma's work environment delivered as if it's completely normal. Great character backstory reveal."
    },
    {
      "index": 51,
      "text": "That's why you know even though you're not my dad, you're like an old brother to me. Like a cool uncle, but old. Like a grandpa. But cool like a son.",
      "characters": [
        "Andy"
      ],
      "joke_types": [
        "character_comedy",
        "escalation"
      ],
      "setup": "Andy trying to define his relationship with Ron",
      "punchline": "His logic completely breaking down and becoming circular",
      "craft_total": 7.03,
      "impact_score": 6.5,
      "quotability": 6.0,
      "rewatch_bonus": 0,
      "is_callback": 0,
      "explanation": "Classic Andy - his attempt to categorize relationships becomes increasingly confused and contradictory. Shows his childlike reasoning process."
    },
    {
      "index": 52,
      "text": "That's right, dickweed. You wanna talk deal? Because my prices have gone up ever so slightly since I saw you last.",
      "characters": [
        "Harvey"
      ],
      "joke_types": [
        "character_comedy",
        "escalation"
      ],
      "setup": "Harvey revealing he owns the coffee shop too",
      "punchline": "His petty escalation and casual profanity",
      "craft_total": 6.1,
      "impact_score": 5.5,
      "quotability": 5.5,
      "rewatch_bonus": 0,
      "is_callback": 0,
      "explanation": "Harvey's pettiness and business monopoly escalating. The casual profanity shows his true colors when he has leverage."
    },
    {
      "index": 53,
      "text": "Yes. I own every tent store in Southern Indiana. Tent Town, Rent Ten Tents, the Tent Offensive, and Ace Tentura Tent Detective.",
      "characters": [
        "Harvey"
      ],
      "joke_types": [
        "wordplay_pun",
        "escalation"
      ],
      "setup": "Harvey revealing his business empire",
      "punchline": "The increasingly ridiculous tent-themed business names",
      "craft_total": 7.47,
      "impact_score": 7.67,
      "quotability": 8.5,
      "rewatch_bonus": 1,
      "is_callback": 0,
      "explanation": "Excellent wordplay escalation - each tent pun gets more elaborate and ridiculous. 'Ace Tentura' is particularly clever, combining Ace Ventura with tent."
    },
    {
      "index": 54,
      "text": "I also own a chick-fil-a franchise, but that's not doing so hot right now. Whatever.",
      "characters": [
        "Harvey"
      ],
      "joke_types": [
        "observational",
        "character_comedy"
      ],
      "setup": "Harvey listing his business empire",
      "punchline": "Casual dismissal of his struggling fast food business",
      "craft_total": 6.7,
      "impact_score": 6.0,
      "quotability": 5.5,
      "rewatch_bonus": 0,
      "is_callback": 0,
      "explanation": "Good character beat showing Harvey's casual attitude toward business failures"
    },
    {
      "index": 55,
      "text": "I also own a chick-fil-a franchise, but that's not doing so hot right now. Whatever.",
      "characters": [
        "Harvey"
      ],
      "joke_types": [
        "character_comedy",
        "observational"
      ],
      "setup": "Harvey listing his business empire",
      "punchline": "The casual mention of his failing Chick-fil-A",
      "craft_total": 6.77,
      "impact_score": 6.17,
      "quotability": 5.5,
      "rewatch_bonus": 0,
      "is_callback": 0,
      "explanation": "Good character detail - shows Harvey's business ventures aren't all successful. The casual dismissal of failure adds to his character."
    },
    {
      "index": 56,
      "text": "You've reached the Tentagon. How can I help you, buttface?",
      "characters": [
        "Harvey"
      ],
      "joke_types": [
        "wordplay_pun",
        "escalation"
      ],
      "setup": "Tom calling another tent store",
      "punchline": "Another Harvey business with Pentagon/tent wordplay and his rude greeting",
      "craft_total": 7.1,
      "impact_score": 6.5,
      "quotability": 7.5,
      "rewatch_bonus": 1,
      "is_callback": 1,
      "explanation": "Great callback with another clever tent pun. 'Tentagon' is inspired wordplay, and the immediate hostility is funny escalation."
    },
    {
      "index": 57,
      "text": "Although, when I was in college I found out that my dad had a second family. Well, we were the second family, technically.",
      "characters": [
        "Shauna"
      ],
      "joke_types": [
        "dark_subversive",
        "character_comedy"
      ],
      "setup": "Shauna bonding over being an only child",
      "punchline": "The dark revelation about family secrets delivered casually",
      "craft_total": 7.1,
      "impact_score": 6.67,
      "quotability": 6.0,
      "rewatch_bonus": 0,
      "is_callback": 0,
      "explanation": "Good character depth - Shauna's casual revelation of family trauma shows why she makes poor choices. The 'technically' correction makes it darker."
    },
    {
      "index": 58,
      "text": "Although there is a tiny part of me that always thought it was just Chris talking into a mirror.",
      "characters": [
        "Shauna"
      ],
      "joke_types": [
        "character_comedy",
        "observational"
      ],
      "setup": "Shauna suggesting Leslie see Chris's therapist",
      "punchline": "Her theory about Chris's therapy sessions",
      "craft_total": 7.33,
      "impact_score": 7.33,
      "quotability": 7.5,
      "rewatch_bonus": 1,
      "is_callback": 0,
      "explanation": "Brilliant character insight - perfectly captures Chris's self-absorbed nature. The image of him having therapy sessions with his own reflection is spot-on."
    },
    {
      "index": 59,
      "text": "Why would you do that? Oh, right. 'Cause calories.",
      "characters": [
        "Andy",
        "Ron"
      ],
      "joke_types": [
        "character_comedy",
        "absurdist"
      ],
      "setup": "Andy eating peanut brittle with a hurt tooth",
      "punchline": "His nonsensical calorie logic for making his injury worse",
      "craft_total": 6.73,
      "impact_score": 6.0,
      "quotability": 5.5,
      "rewatch_bonus": 0,
      "is_callback": 0,
      "explanation": "Pure Andy logic - applying food rules illogically to justify bad decisions. Ron's incredulous response sells the absurdity."
    },
    {
      "index": 60,
      "text": "It's called Sweaty Roger's Pants Tent.",
      "characters": [
        "Tom"
      ],
      "joke_types": [
        "wordplay_pun",
        "visual_gag"
      ],
      "setup": "Looking for alternative tent stores",
      "punchline": "The gross-sounding store name",
      "craft_total": 6.1,
      "impact_score": 5.5,
      "quotability": 6.0,
      "rewatch_bonus": 0,
      "is_callback": 0,
      "explanation": "Mild gross-out humor with pun elements - functional but not exceptional"
    },
    {
      "index": 61,
      "text": "Nobody can match your ethnic hybrid energy.",
      "characters": [
        "Leslie"
      ],
      "joke_types": [
        "character_comedy",
        "observational"
      ],
      "setup": "Leslie explaining why other friends don't measure up",
      "punchline": "The awkward phrasing of Ann's mixed heritage",
      "craft_total": 6.55,
      "impact_score": 6.0,
      "quotability": 6.5,
      "rewatch_bonus": 0,
      "is_callback": 0,
      "explanation": "Leslie's awkward but well-meaning attempt to celebrate diversity"
    },
    {
      "index": 62,
      "text": "You shut your mouth. You have all the strengths.",
      "characters": [
        "Leslie"
      ],
      "joke_types": [
        "character_comedy",
        "cringe_discomfort"
      ],
      "setup": "Ann suggesting others have unique strengths",
      "punchline": "Leslie's aggressive denial of any weakness in Ann",
      "craft_total": 6.53,
      "impact_score": 6.0,
      "quotability": 6.5,
      "rewatch_bonus": 0,
      "is_callback": 0,
      "explanation": "Classic Leslie - her inability to accept any criticism of Ann, even positive. The aggressive tone makes it funnier."
    },
    {
      "index": 63,
      "text": "Yeah, 'cause Riggins is a criminal. He took the fall for his brother. Okay, he didn't watch out for his brother. You know, I'm not having this conversation with you again. That family is garbage.",
      "characters": [
        "Leslie",
        "Ann"
      ],
      "joke_types": [
        "character_comedy",
        "escalation"
      ],
      "setup": "Ann and Leslie disagreeing about Friday Night Lights characters",
      "punchline": "Leslie's passionate hatred of the Riggins family escalating to calling them garbage",
      "craft_total": 7.2,
      "impact_score": 6.67,
      "quotability": 6.5,
      "rewatch_bonus": 0,
      "is_callback": 0,
      "explanation": "Good character work showing Leslie's moral absolutism extended to fictional characters. The escalating criticism is appropriately passionate."
    },
    {
      "index": 64,
      "text": "Yeah, 'cause Riggins is a criminal.",
      "characters": [
        "Leslie"
      ],
      "joke_types": [
        "character_comedy",
        "setup_punchline"
      ],
      "setup": "Ann preferring the bad boy Riggins character",
      "punchline": "Leslie's moral judgment of fictional character",
      "craft_total": 7.07,
      "impact_score": 6.5,
      "quotability": 5.5,
      "rewatch_bonus": 0,
      "is_callback": 0,
      "explanation": "Good Leslie character moment showing her black-and-white morality extending to TV"
    },
    {
      "index": 65,
      "text": "I almost bought a toe ring the other day. What? Ann, you're somebody's mother.",
      "characters": [
        "Leslie",
        "Ann"
      ],
      "joke_types": [
        "character_comedy",
        "cringe_discomfort"
      ],
      "setup": "Leslie mentioning something she wants to talk about",
      "punchline": "Her horrified reaction to Ann considering a toe ring as a mother",
      "craft_total": 6.7,
      "impact_score": 6.0,
      "quotability": 6.0,
      "rewatch_bonus": 0,
      "is_callback": 0,
      "explanation": "Leslie's moral panic over a toe ring shows her conservative side about motherhood. The escalation from casual mention to moral outrage works."
    },
    {
      "index": 66,
      "text": "When it's all said and done, there were a few mazes I'd cheated on. Also, the inside of my mouth is black and hot.",
      "characters": [
        "Andy"
      ],
      "joke_types": [
        "character_comedy",
        "non_sequitur"
      ],
      "setup": "Andy reflecting on his dentist experience",
      "punchline": "His confession about cheating on magazine puzzles combined with dental discomfort",
      "craft_total": 6.67,
      "impact_score": 6.0,
      "quotability": 6.0,
      "rewatch_bonus": 0,
      "is_callback": 1,
      "explanation": "Andy's confession about cheating combined with his dental description is perfectly random and childlike. Good callback to earlier setup."
    },
    {
      "index": 67,
      "text": "So do I strip down to my underwear, or all the way naked?",
      "characters": [
        "Andy"
      ],
      "joke_types": [
        "character_comedy",
        "absurdist"
      ],
      "setup": "Andy at the dentist",
      "punchline": "His confusion about dental procedure clothing requirements",
      "craft_total": 6.75,
      "impact_score": 6.25,
      "quotability": 5.5,
      "rewatch_bonus": 0,
      "is_callback": 0,
      "explanation": "Classic Andy confusion - applying wrong medical procedure expectations to dental work. Shows his fundamental misunderstanding of basic situations."
    },
    {
      "index": 68,
      "text": "Gentlemen, I've won two online satellite Jamaican poker tournaments. I can tell that you're bluffing.",
      "characters": [
        "Harvey"
      ],
      "joke_types": [
        "character_comedy",
        "absurdist"
      ],
      "setup": "Harvey claiming to know they're bluffing",
      "punchline": "The ridiculously specific and fake-sounding poker credentials",
      "craft_total": 7.07,
      "impact_score": 6.67,
      "quotability": 7.5,
      "rewatch_bonus": 1,
      "is_callback": 0,
      "explanation": "Perfect Harvey moment - the oddly specific and probably fabricated poker credentials delivered with complete confidence. 'Satellite Jamaican' is particularly absurd."
    },
    {
      "index": 69,
      "text": "I am. And I was bluffing about winning those tournaments.",
      "characters": [
        "Harvey"
      ],
      "joke_types": [
        "character_comedy",
        "irony_sarcasm"
      ],
      "setup": "Harvey's poker credentials being questioned",
      "punchline": "His immediate admission that he made everything up",
      "craft_total": 7.03,
      "impact_score": 6.67,
      "quotability": 6.5,
      "rewatch_bonus": 0,
      "is_callback": 1,
      "explanation": "Nice immediate deflation of Harvey's bluster. His honesty about lying is unexpectedly refreshing and shows he's not completely delusional."
    },
    {
      "index": 70,
      "text": "Second of all, I got a Tin Cup Blu-Ray itching for a Rene Russo signature.",
      "characters": [
        "Tom"
      ],
      "joke_types": [
        "callback",
        "character_comedy"
      ],
      "setup": "Tom negotiating terms",
      "punchline": "His personal request for celebrity memorabilia from the tents",
      "craft_total": 6.65,
      "impact_score": 5.75,
      "quotability": 5.5,
      "rewatch_bonus": 0,
      "is_callback": 1,
      "explanation": "Good callback and Tom character moment, though somewhat expected"
    },
    {
      "index": 71,
      "text": "Oh, hey. I'm Larry. Great to know you. I love tent world.",
      "characters": [
        "Larry"
      ],
      "joke_types": [
        "character_comedy",
        "cringe_discomfort"
      ],
      "setup": "Larry being introduced as the guy who brought Harvey down",
      "punchline": "His enthusiastic, friendly greeting to the man he just defeated",
      "craft_total": 6.7,
      "impact_score": 6.25,
      "quotability": 5.5,
      "rewatch_bonus": 0,
      "is_callback": 0,
      "explanation": "Perfect Larry moment - his innocent friendliness even toward someone who was scamming them. Shows his genuine, oblivious nature."
    },
    {
      "index": 72,
      "text": "God! Can you just be cool for one second?",
      "characters": [
        "Tom"
      ],
      "joke_types": [
        "character_comedy",
        "cringe_discomfort"
      ],
      "setup": "Larry being friendly to Harvey",
      "punchline": "Tom's frustrated plea for Larry to read the room",
      "craft_total": 6.63,
      "impact_score": 6.17,
      "quotability": 5.0,
      "rewatch_bonus": 0,
      "is_callback": 0,
      "explanation": "Standard Tom frustration with Larry's social obliviousness. Gets the job done but not particularly creative."
    },
    {
      "index": 73,
      "text": "Press the paw. Hi, Leslie. It's Ann. I love you, and everything's gonna be okay.",
      "characters": [
        "April",
        "Donna",
        "Ann"
      ],
      "joke_types": [
        "character_comedy",
        "setup_punchline"
      ],
      "setup": "April and Donna giving Leslie a gift",
      "punchline": "The sweet but slightly patronizing recorded message",
      "craft_total": 6.93,
      "impact_score": 6.5,
      "quotability": 6.0,
      "rewatch_bonus": 0,
      "is_callback": 0,
      "explanation": "Sweet gesture that's also slightly condescending - treating Leslie like a child who needs comfort. Shows their friendship in a tangible way."
    },
    {
      "index": 74,
      "text": "Mm, you touch me and I stab the bunny.",
      "characters": [
        "April"
      ],
      "joke_types": [
        "character_comedy",
        "dark_subversive"
      ],
      "setup": "Leslie suggesting a five-minute hug tradition",
      "punchline": "April's threat to destroy the gift to avoid physical affection",
      "craft_total": 7.0,
      "impact_score": 6.5,
      "quotability": 8.0,
      "rewatch_bonus": 1,
      "is_callback": 0,
      "explanation": "Perfect April - threatening violence against an innocent object to avoid human affection. The economy and character specificity are excellent."
    },
    {
      "index": 75,
      "text": "I'm just an impartial bunny, but I think Ann sucks. Also-- I'm the zodiac killer.",
      "characters": [
        "April"
      ],
      "joke_types": [
        "character_comedy",
        "dark_subversive"
      ],
      "setup": "April presumably making the bunny 'talk'",
      "punchline": "The bunny's increasingly dark messages",
      "craft_total": 7.73,
      "impact_score": 7.5,
      "quotability": 8.5,
      "rewatch_bonus": 1,
      "is_callback": 0,
      "explanation": "Brilliant April moment - using the innocent gift to express her dark thoughts. The escalation from hating Ann to serial killer confession is perfectly absurd."
    },
    {
      "index": 76,
      "text": "Also-- I'm the zodiac killer.",
      "characters": [
        "April"
      ],
      "joke_types": [
        "dark_subversive",
        "escalation"
      ],
      "setup": "April making the bunny voice her opinions",
      "punchline": "Escalating to absurd criminal confession",
      "craft_total": 7.55,
      "impact_score": 7.25,
      "quotability": 8.5,
      "rewatch_bonus": 1,
      "is_callback": 0,
      "explanation": "Excellent April escalation - perfect dark humor and absurdist confession. Highly quotable and completely unexpected"
    },
    {
      "index": 77,
      "text": "Your inhaler is hidden under the pile of pistachio shells on my desk, obviously.",
      "characters": [
        "Tom"
      ],
      "joke_types": [
        "character_comedy",
        "absurdist"
      ],
      "setup": "Larry looking for his inhaler",
      "punchline": "Tom's sarcastic suggestion involving his pistachio habit",
      "craft_total": 6.7,
      "impact_score": 6.0,
      "quotability": 5.0,
      "rewatch_bonus": 0,
      "is_callback": 0,
      "explanation": "Sets up the allergy joke but is mostly functional. Tom's sarcasm is in character but not particularly inspired."
    },
    {
      "index": 78,
      "text": "Okay, well, that's funny, 'cause I'm terribly allergic to pistachios.",
      "characters": [
        "Larry"
      ],
      "joke_types": [
        "irony_sarcasm",
        "character_comedy"
      ],
      "setup": "Tom mentioning pistachios sarcastically",
      "punchline": "Larry's serious allergy revelation making Tom look bad",
      "craft_total": 7.03,
      "impact_score": 6.5,
      "quotability": 6.0,
      "rewatch_bonus": 0,
      "is_callback": 0,
      "explanation": "Good reversal - Tom's casual cruelty backfires when Larry's genuine medical condition makes him look terrible. Sets up the defense speech nicely."
    },
    {
      "index": 79,
      "text": "I like Larry. He is a good friend and a fine man with an inexplicably gorgeous wife-- I mean, to the point where it makes no sense at all.",
      "characters": [
        "Ben"
      ],
      "joke_types": [
        "character_comedy",
        "observational"
      ],
      "setup": "Ben defending Larry",
      "punchline": "His genuine defense derailed by confusion about Gayle's attractiveness",
      "craft_total": 7.57,
      "impact_score": 7.17,
      "quotability": 7.5,
      "rewatch_bonus": 1,
      "is_callback": 0,
      "explanation": "Excellent character moment - Ben's genuine desire to defend Larry gets sidetracked by his honest bewilderment. The self-correction makes it funnier."
    },
    {
      "index": 80,
      "text": "O, captain, my captain.",
      "characters": [
        "Ben"
      ],
      "joke_types": [
        "character_comedy",
        "escalation"
      ],
      "setup": "Ben's defense of Larry getting passionate",
      "punchline": "His dramatic Dead Poets Society reference for Larry",
      "craft_total": 6.7,
      "impact_score": 6.33,
      "quotability": 6.5,
      "rewatch_bonus": 0,
      "is_callback": 0,
      "explanation": "Ben's dramatic escalation using literary references for Larry. The mismatch between high culture and Larry is appropriately absurd."
    },
    {
      "index": 81,
      "text": "Got so startled I tooted.",
      "characters": [
        "Larry"
      ],
      "joke_types": [
        "physical_slapstick",
        "character_comedy"
      ],
      "setup": "Larry being moved by Ben's defense",
      "punchline": "His embarrassing physical reaction to emotional moments",
      "craft_total": 6.57,
      "impact_score": 6.0,
      "quotability": 5.5,
      "rewatch_bonus": 0,
      "is_callback": 0,
      "explanation": "Classic Larry - his emotional response manifests physically in an embarrassing way. The word 'tooted' is appropriately childish."
    }
  ],
  "imdb_rating": 7.5,
  "imdb_votes": 2069,
  "tmdb_overview": null,
  "air_date": null,
  "still_path": null,
  "guest_stars": null,
  "war": null,
  "humor_index_v1": 72.3,
  "ci_95_low": 70.3,
  "ci_95_high": 76.1,
  "percentile_in_show": 15.3,
  "zscore_in_show": -1.05,
  "zscore_in_season": -1.29,
  "humor_index_single_run": 78.6,
  "standup_jokes": 0,
  "standup_fraction": 0.0,
  "consensus_runs": 3,
  "consensus_method": "3-run consensus"
}